[{"rs_artist":"LIONEL RICHIE","rs_track":"Dancing On The Ceiling","rs_youtube_id":"ovo6zwv6DX4","time":"23:51","rs_id":"20565038","f_time":"2024.10.23. 23:51","itunes_pic":"Music125\/v4\/0d\/c0\/a3\/0dc0a301-d9e5-2980-5141-d8ddb1571398\/00602498607497.rgb.jpg"},{"rs_artist":"BILLY JOEL","rs_track":"Uptown Girl","rs_youtube_id":"hCuMWrfXG4E","time":"23:48","rs_id":"20564931","f_time":"2024.10.23. 23:48","itunes_pic":"Music125\/v4\/f0\/7a\/54\/f07a54ab-3ebc-6813-e515-86200b8138fc\/dj.uthntyfe.jpg"},{"rs_artist":"ERIC CLAPTON","rs_track":"Layla","rs_youtube_id":"pKwQlm-wldA","time":"23:44","rs_id":"20564785","f_time":"2024.10.23. 23:44","itunes_pic":"Music115\/v4\/2b\/55\/08\/2b550878-8bad-b40f-9a58-d63aca53c824\/00602498206034.rgb.jpg"},{"rs_artist":"MARIANNE ROSENBERG","rs_track":"Ich Bin Wie Du","rs_youtube_id":"DiebMADvbPc","time":"23:40","rs_id":"20564662","f_time":"2024.10.23. 23:40","itunes_pic":"Music123\/v4\/19\/23\/d3\/1923d3d8-e370-d5c7-e105-656b73e401f0\/cover.jpg"},{"rs_artist":"CHRISTOPHER CROSS","rs_track":"Ride Like The Wind","rs_youtube_id":"qySwjyr1W0k","time":"23:36","rs_id":"20564532","f_time":"2024.10.23. 23:36","itunes_pic":"Music116\/v4\/6d\/a6\/30\/6da6309d-c846-367e-40aa-007b87477a15\/075992338363.png"},{"rs_artist":"RICK ASTLEY","rs_track":"Never Gonna Give You Up","rs_youtube_id":"dQw4w9WgXcQ","time":"23:33","rs_id":"20564407","f_time":"2024.10.23. 23:33","itunes_pic":"Music126\/v4\/b3\/21\/d3\/b321d3e4-edfe-124b-d0cd-a64ad1df3290\/4050538793840.jpg"},{"rs_artist":"BLONDIE","rs_track":"Heart Of Glass","rs_youtube_id":"WGU_4-5RaxU","time":"23:26","rs_id":"20564182","f_time":"2024.10.23. 23:26","itunes_pic":"Music115\/v4\/86\/21\/c4\/8621c47c-19a2-ebca-a63a-45ae7017556f\/14ULAIM00403.rgb.jpg"},{"rs_artist":"INNER CIRCLE","rs_track":"Sweat (A La La La La Long)","rs_youtube_id":"uc2UEfWjvo8","time":"23:22","rs_id":"20564055","f_time":"2024.10.23. 23:22","itunes_pic":"Music126\/v4\/9d\/b5\/1a\/9db51a84-fa24-7cb6-e7b3-fe8bd03d9464\/196922644849.jpg"},{"rs_artist":"U2","rs_track":"New Year's Day","rs_youtube_id":"jeYCyCaK_5k","time":"23:18","rs_id":"20563899","f_time":"2024.10.23. 23:18","itunes_pic":"Music115\/v4\/d9\/cd\/b2\/d9cdb23f-37a3-9c90-4bbf-e4b99c6b8228\/17UMGIM84937.rgb.jpg"},{"rs_artist":"ABBA","rs_track":"The Winner Takes It All","rs_youtube_id":"92cwKCU8Z5c","time":"23:13","rs_id":"20563740","f_time":"2024.10.23. 23:13","itunes_pic":"Music115\/v4\/60\/f8\/a6\/60f8a6bc-e875-238d-f2f8-f34a6034e6d2\/14UMGIM07615.rgb.jpg"},{"rs_artist":"TERENCE TRENT D'ARBY","rs_track":"Dance Little Sister","rs_youtube_id":"OlmKCj03fHw","time":"23:09","rs_id":"20563619","f_time":"2024.10.23. 23:09","itunes_pic":"Music126\/v4\/09\/49\/00\/094900cb-76ab-4aa2-7048-edb9ef0bc3d3\/888880752093.jpg"},{"rs_artist":"PHIL COLLINS","rs_track":"Something Happened On The Way To Heaven","rs_youtube_id":"CKrGj73OsAY","time":"23:06","rs_id":"20563488","f_time":"2024.10.23. 23:06","itunes_pic":"Music115\/v4\/1c\/83\/f9\/1c83f950-aa62-aeb7-f561-21d9541514ba\/dj.wxggooob.jpg"},{"rs_artist":"THE POLICE","rs_track":"Every Breath You Take","rs_youtube_id":"OMOGaugKpzs","time":"23:01","rs_id":"20563339","f_time":"2024.10.23. 23:01","itunes_pic":"Music211\/v4\/42\/b7\/db\/42b7dbe1-d13f-c600-5b78-daa57c5d0f08\/06UMGIM50761.rgb.jpg"},{"rs_artist":"BRYAN ADAMS & MELANIE C","rs_track":"When You're Gone","rs_youtube_id":"_W2jONIjrM0","time":"22:50","rs_id":"20562981","f_time":"2024.10.23. 22:50","itunes_pic":"Music124\/v4\/8e\/3e\/53\/8e3e538f-4740-a3e1-cb0a-88de94d6ce82\/17UM1IM30968.rgb.jpg"},{"rs_artist":"PRINCE & THE REVOLUTION","rs_track":"I Would Die 4 U","rs_youtube_id":"hkNl3pq1twE","time":"22:46","rs_id":"20562870","f_time":"2024.10.23. 22:46","itunes_pic":"Music125\/v4\/b7\/44\/ca\/b744ca9b-9b29-e934-3d59-5da099a83ce3\/mzi.shgvhklf.jpg"},{"rs_artist":"TONY ESPOSITO","rs_track":"Papa Chico","rs_youtube_id":"jpxZnjPMy_o","time":"22:43","rs_id":"20562743","f_time":"2024.10.23. 22:43","itunes_pic":"Music\/0c\/bf\/a9\/mzi.jqpkufgl.jpg"},{"rs_artist":"KATE BUSH","rs_track":"Wuthering Heights","rs_youtube_id":"-1pMMIe4hb4","time":"22:39","rs_id":"20562636","f_time":"2024.10.23. 22:39","itunes_pic":"Music126\/v4\/4f\/a8\/69\/4fa8697c-baf0-8dc2-8609-190a50432952\/cover.jpg"},{"rs_artist":"MICHAEL JACKSON","rs_track":"Wanna Be Startin' Somethin'","rs_youtube_id":"1XMvPTFzgVU","time":"22:35","rs_id":"20562472","f_time":"2024.10.23. 22:35","itunes_pic":"Music125\/v4\/3d\/9d\/38\/3d9d3811-71f0-3a0e-1ada-3004e56ff852\/827969428726.jpg"},{"rs_artist":"LONDON BEAT","rs_track":"I've Been Thinking About You","rs_youtube_id":"dGw3w_njQ4g","time":"22:26","rs_id":"20562190","f_time":"2024.10.23. 22:26","itunes_pic":"Music\/y2005\/m05\/d18\/h03\/s05.txsgrgtz.tif"},{"rs_artist":"ELECTRIC LIGHT ORCHESTRA","rs_track":"Mr. Blue Sky","rs_youtube_id":"aQUlA8Hcv4s","time":"22:20","rs_id":"20562017","f_time":"2024.10.23. 22:20","itunes_pic":"Features125\/v4\/c8\/13\/ea\/c813ea8b-0caa-2a8f-0efa-4d2442c20704\/dj.mjqtnksw.jpg"},{"rs_artist":"DOE MAAR","rs_track":"Sinds 1 Dag Of 2 (32 Jaar)","rs_youtube_id":"f15dEJgC-nU","time":"22:17","rs_id":"20561908","f_time":"2024.10.23. 22:17","itunes_pic":"Music\/df\/ca\/a7\/mzi.yiyhxqdk.jpg"},{"rs_artist":"NIK KERSHAW","rs_track":"I Won't Let The Sun Go Down On Me","rs_youtube_id":"4CXLfUTWeHI","time":"22:14","rs_id":"20561809","f_time":"2024.10.23. 22:14","itunes_pic":"Music114\/v4\/d9\/63\/6d\/d9636d4d-2957-c646-d7de-5db31ca54886\/mzi.kronjohh.jpg"},{"rs_artist":"JOSHUA KADISON","rs_track":"Jessie","rs_youtube_id":"eHiFBw13BwY","time":"22:11","rs_id":"20561703","f_time":"2024.10.23. 22:11","itunes_pic":"Music128\/v4\/9a\/cc\/0c\/9acc0cd5-fa4d-9515-48c1-117c525c953a\/00077778092056.rgb.jpg"},{"rs_artist":"YVONNE ELLIMAN","rs_track":"If I Can't Have You","rs_youtube_id":"CZVUzho-nok","time":"22:08","rs_id":"20561610","f_time":"2024.10.23. 22:08","itunes_pic":"Music113\/v4\/74\/c1\/73\/74c17380-b75d-4d74-31d8-99f8e8b20c36\/17UM1IM27905.rgb.jpg"},{"rs_artist":"MADONNA","rs_track":"Borderline","rs_youtube_id":"rSaC-YbSDpo","time":"22:04","rs_id":"20561463","f_time":"2024.10.23. 22:04","itunes_pic":"Music\/y2005\/m09\/d19\/h20\/mzi.ykiinwgl.jpg"},{"rs_artist":"ORCHESTRAL MANOEUVRES IN THE DARK","rs_track":"(Forever) Live And Die","rs_youtube_id":"moFiaQPCl04","time":"21:51","rs_id":"20561098","f_time":"2024.10.23. 21:51","itunes_pic":"Music125\/v4\/d0\/9e\/fa\/d09efa3b-f49a-f456-d26d-5a1cca158344\/00094636459752.rgb.jpg"},{"rs_artist":"EAGLES","rs_track":"Hotel California","rs_youtube_id":"09839DpTctU","time":"21:41","rs_id":"20560759","f_time":"2024.10.23. 21:41","itunes_pic":"Features114\/v4\/e4\/6c\/3d\/e46c3d30-9a32-b984-ee6f-ea473723a651\/contsched.tidyyafg.jpg"},{"rs_artist":"ENRIQUE IGLESIAS","rs_track":"Bailamos","rs_youtube_id":"5sye_VxmNZA","time":"21:36","rs_id":"20560598","f_time":"2024.10.23. 21:36","itunes_pic":"Music211\/v4\/a5\/ef\/33\/a5ef33a4-b683-5ee8-664e-c7a181b3af18\/4099496747366.jpg"},{"rs_artist":"LEVEL 42","rs_track":"Lessons In Love","rs_youtube_id":"9x1RcVrGjGM","time":"21:33","rs_id":"20560474","f_time":"2024.10.23. 21:33","itunes_pic":""},{"rs_artist":"CHRIS NORMAN & SUZI QUATRO","rs_track":"Stumblin' In","rs_youtube_id":"Z1PcY59AX2Q","time":"21:23","rs_id":"20560169","f_time":"2024.10.23. 21:23","itunes_pic":"Music\/51\/69\/c1\/mzi.hxpuycpj.jpg"},{"rs_artist":"BON JOVI","rs_track":"You Give Love A Bad Name","rs_youtube_id":"KrZHPOeOxQQ","time":"21:19","rs_id":"20560059","f_time":"2024.10.23. 21:19","itunes_pic":"Music112\/v4\/40\/16\/3e\/40163e24-6985-b785-d4ea-cbae07d74812\/06UMGIM05422.rgb.jpg"},{"rs_artist":"BILLY JOEL","rs_track":"The River Of Dreams","rs_youtube_id":"hSq4B_zHqPM","time":"21:15","rs_id":"20559925","f_time":"2024.10.23. 21:15","itunes_pic":"Music125\/v4\/f0\/7a\/54\/f07a54ab-3ebc-6813-e515-86200b8138fc\/dj.uthntyfe.jpg"},{"rs_artist":"BONEY M","rs_track":"Ma Baker","rs_youtube_id":"9c5yPIQ3LQI","time":"21:11","rs_id":"20559785","f_time":"2024.10.23. 21:11","itunes_pic":"Music\/73\/6b\/8e\/mzi.irnviydz.jpg"},{"rs_artist":"JOE COCKER & JENNIFER WARNES","rs_track":"Up Where We Belong","rs_youtube_id":"bjrOcrisGyI","time":"21:06","rs_id":"20559628","f_time":"2024.10.23. 21:06","itunes_pic":"Music126\/v4\/45\/bc\/c5\/45bcc533-2360-4f8d-b783-343c13d6b800\/06UMGIM03749.rgb.jpg"},{"rs_artist":"BRUCE SPRINGSTEEN","rs_track":"Dancing In The Dark","rs_youtube_id":"CSggjP_I0KM","time":"21:02","rs_id":"20559499","f_time":"2024.10.23. 21:02","itunes_pic":"Music221\/v4\/f4\/8d\/10\/f48d105a-ddd6-baac-a584-d0550f901085\/198846087788.jpg"},{"rs_artist":"ALPHAVILLE","rs_track":"Big In Japan","rs_youtube_id":"tl6u2NASUzU","time":"20:51","rs_id":"20559149","f_time":"2024.10.23. 20:51","itunes_pic":"Music125\/v4\/c9\/f5\/e6\/c9f5e66e-8ab1-5c75-dbe7-7670f9204776\/s06.emtrcgpz.jpg"},{"rs_artist":"POINTER SISTERS","rs_track":"Fire","rs_youtube_id":"K9S5EZgIJck","time":"20:47","rs_id":"20559039","f_time":"2024.10.23. 20:47","itunes_pic":"Features114\/v4\/64\/13\/db\/6413db84-4325-81e8-df43-ac7567389520\/dj.zvelubll.jpg"},{"rs_artist":"FRANKIE GOES TO HOLLYWOOD","rs_track":"Relax","rs_youtube_id":"Yem_iEHiyJ0","time":"20:43","rs_id":"20558908","f_time":"2024.10.23. 20:43","itunes_pic":"Music124\/v4\/59\/f5\/7e\/59f57eb5-0432-d496-9dc9-6ff1ef770a7d\/00602537068388.rgb.jpg"},{"rs_artist":"BACKSTREET BOYS","rs_track":"Everybody (Backstreet's Back)","rs_youtube_id":"6M6samPEMpM","time":"20:40","rs_id":"20558791","f_time":"2024.10.23. 20:40","itunes_pic":"Music2\/v4\/7f\/84\/e7\/7f84e766-b755-46d2-678f-d35257d8d2fe\/886443959590.jpg"},{"rs_artist":"HUMAN LEAGUE","rs_track":"Human","rs_youtube_id":"s1ysoohV_zA","time":"20:36","rs_id":"20558674","f_time":"2024.10.23. 20:36","itunes_pic":"Music124\/v4\/b2\/ab\/29\/b2ab29c9-add0-65cf-070e-933cca1daefa\/13UABIM56759.rgb.jpg"},{"rs_artist":"ABBA","rs_track":"Waterloo","rs_youtube_id":"Sj_9CiNkkn4","time":"20:33","rs_id":"20558577","f_time":"2024.10.23. 20:33","itunes_pic":"Music115\/v4\/60\/f8\/a6\/60f8a6bc-e875-238d-f2f8-f34a6034e6d2\/14UMGIM07615.rgb.jpg"},{"rs_artist":"UB40","rs_track":"Red Red Wine","rs_youtube_id":"zXt56MB-3vc","time":"20:30","rs_id":"20558481","f_time":"2024.10.23. 20:30","itunes_pic":"Music125\/v4\/84\/c2\/52\/84c25239-f4a6-1b09-c046-9669784497d6\/00077778641254.rgb.jpg"},{"rs_artist":"DE DIJK","rs_track":"Als Ze Er Niet Is","rs_youtube_id":"vn_pUxADmoY","time":"20:22","rs_id":"20558231","f_time":"2024.10.23. 20:22","itunes_pic":"Music113\/v4\/a8\/cf\/4a\/a8cf4acb-1a5a-6d74-9471-d3a29cbecf97\/06UMGIM37126.rgb.jpg"},{"rs_artist":"ANITA MEYER","rs_track":"Why Tell Me Why","rs_youtube_id":"fuluEbNVbBw","time":"20:17","rs_id":"20558077","f_time":"2024.10.23. 20:17","itunes_pic":"Music\/18\/42\/45\/mzi.urxdccie.jpg"},{"rs_artist":"ALICE COOPER","rs_track":"How You Gonna See Me Now","rs_youtube_id":"c_Bv8UkzW7g","time":"20:13","rs_id":"20557950","f_time":"2024.10.23. 20:13","itunes_pic":"Music124\/v4\/47\/70\/16\/477016e2-f7ae-7cc9-8197-3a4916c28088\/mzi.qdvxygpa.jpg"},{"rs_artist":"CHARLES & EDDIE","rs_track":"Would I Lie To You","rs_youtube_id":"G_UXvcr22rM","time":"20:08","rs_id":"20557782","f_time":"2024.10.23. 20:08","itunes_pic":"Music112\/v4\/81\/41\/3f\/81413fe1-117e-4ab3-c705-ed2c560764cf\/13UABIM52178.rgb.jpg"},{"rs_artist":"U2","rs_track":"Sunday Bloody Sunday","rs_youtube_id":"EM4vblG6BVQ","time":"20:03","rs_id":"20557631","f_time":"2024.10.23. 20:03","itunes_pic":"Music113\/v4\/a0\/8b\/af\/a08baf07-1995-fcc7-661d-1e436f7ba39b\/22UM1IM44827.rgb.jpg"},{"rs_artist":"ROBBIE WILLIAMS","rs_track":"Let Me Entertain You","rs_youtube_id":"ymPu2PdLW3I","time":"19:51","rs_id":"20557256","f_time":"2024.10.23. 19:51","itunes_pic":"Music124\/v4\/6f\/fe\/2b\/6ffe2b0e-df9d-ab6f-220e-79785b0bdb6c\/13UMGIM19711.rgb.jpg"},{"rs_artist":"SOUL II SOUL","rs_track":"Back To Life","rs_youtube_id":"TB54dZkzZOY","time":"19:47","rs_id":"20557137","f_time":"2024.10.23. 19:47","itunes_pic":"Music115\/v4\/f9\/32\/d9\/f932d98c-9770-0b22-646d-8c7f2ae20eaf\/dj.lgduffus.jpg"},{"rs_artist":"BEE GEES","rs_track":"How Deep Is Your Love","rs_youtube_id":"XpqqjU7u5Yc","time":"19:43","rs_id":"20556981","f_time":"2024.10.23. 19:43","itunes_pic":"Music113\/v4\/74\/c1\/73\/74c17380-b75d-4d74-31d8-99f8e8b20c36\/17UM1IM27905.rgb.jpg"},{"rs_artist":"CORONA","rs_track":"The Rhythm Of The Night","rs_youtube_id":"OnT58cIJSpw","time":"19:39","rs_id":"20556858","f_time":"2024.10.23. 19:39","itunes_pic":"Music122\/v4\/0f\/1a\/36\/0f1a362d-d376-7e1f-8ade-fff028d52d3c\/825646282784.jpg"},{"rs_artist":"YES","rs_track":"Owner Of A Lonely Heart","rs_youtube_id":"SVOuYquXuuc","time":"19:35","rs_id":"20556711","f_time":"2024.10.23. 19:35","itunes_pic":"Music114\/v4\/7b\/3d\/87\/7b3d8720-d127-db90-88e8-08f27f325524\/603497879922.jpg"},{"rs_artist":"BILLY OCEAN","rs_track":"Get Outta My Dreams Get Into My Car","rs_youtube_id":"zNgcYGgtf8M","time":"19:25","rs_id":"20556387","f_time":"2024.10.23. 19:25","itunes_pic":"Music115\/v4\/a9\/ee\/fd\/a9eefd6d-667d-0d6d-87ff-3da7a5d8361f\/mzi.abkecwqm.jpg"},{"rs_artist":"LIPPS INC.","rs_track":"Funky Town","rs_youtube_id":"uhzy7JaU2Zc","time":"19:21","rs_id":"20556265","f_time":"2024.10.23. 19:21","itunes_pic":"Music211\/v4\/0c\/ca\/b1\/0ccab149-8678-d277-78a0-99e3a6245318\/233286.jpg"},{"rs_artist":"LIONEL RICHIE","rs_track":"Hello","rs_youtube_id":"mHONNcZbwDY","time":"19:17","rs_id":"20556128","f_time":"2024.10.23. 19:17","itunes_pic":"Music125\/v4\/0d\/c0\/a3\/0dc0a301-d9e5-2980-5141-d8ddb1571398\/00602498607497.rgb.jpg"},{"rs_artist":"CHESNEY HAWKES","rs_track":"The One And Only","rs_youtube_id":"ZvMsp7s78Do","time":"19:13","rs_id":"20556008","f_time":"2024.10.23. 19:13","itunes_pic":"Music114\/v4\/5e\/a8\/52\/5ea85284-9390-9706-e41f-ae97dae05a25\/05099902665955.jpg"},{"rs_artist":"PINK FLOYD","rs_track":"Another Brick In The Wall","rs_youtube_id":"5IpYOF4Hi6Q","time":"19:10","rs_id":"20555887","f_time":"2024.10.23. 19:10","itunes_pic":"Music115\/v4\/3c\/b4\/e3\/3cb4e3d0-cd77-8f18-7465-d60e6949b435\/886445635850.jpg"},{"rs_artist":"MIAMI SOUND MACHINE","rs_track":"Conga","rs_youtube_id":"54ItEmCnP80","time":"19:05","rs_id":"20555735","f_time":"2024.10.23. 19:05","itunes_pic":"Music49\/v4\/d2\/ef\/6e\/d2ef6e98-9242-d3f3-97c1-6611b31df4f9\/886445811957.jpg"},{"rs_artist":"PHIL COLLINS","rs_track":"Against All Odds","rs_youtube_id":"wuvtoyVi7vY","time":"19:02","rs_id":"20555626","f_time":"2024.10.23. 19:02","itunes_pic":"Music115\/v4\/1c\/83\/f9\/1c83f950-aa62-aeb7-f561-21d9541514ba\/dj.wxggooob.jpg"},{"rs_artist":"COOLIO & LV","rs_track":"Gangsta's Paradise","rs_youtube_id":"fPO76Jlnz6c","time":"18:48","rs_id":"20555210","f_time":"2024.10.23. 18:48","itunes_pic":"Music125\/v4\/65\/c4\/c5\/65c4c588-0fcd-fb3c-e1b0-5a685cb13040\/dj.iydpynlx.jpg"},{"rs_artist":"THE POLICE","rs_track":"Roxanne","rs_youtube_id":"3T1c7GkzRQQ","time":"18:45","rs_id":"20555106","f_time":"2024.10.23. 18:45","itunes_pic":"Music122\/v4\/13\/a6\/4c\/13a64c50-4281-a678-002d-1df9d833aa06\/06UMGIM50761.rgb.jpg"},{"rs_artist":"RUFUS & CHAKA KHAN","rs_track":"Ain't Nobody","rs_youtube_id":"BNirQXe8HOA","time":"18:41","rs_id":"20554978","f_time":"2024.10.23. 18:41","itunes_pic":"Music127\/v4\/db\/09\/3c\/db093cca-d4f0-e51b-a0e2-5cc794a83946\/084247968835.jpg"},{"rs_artist":"MR. MISTER","rs_track":"Broken Wings","rs_youtube_id":"nKhN1t_7PEY","time":"18:36","rs_id":"20554799","f_time":"2024.10.23. 18:36","itunes_pic":"Music124\/v4\/10\/ba\/dc\/10badcf7-1e8d-fe26-1bff-8cb07cbd4962\/mzi.vpqvxfya.jpg"},{"rs_artist":"EARTH WIND & FIRE","rs_track":"Boogie Wonderland","rs_youtube_id":"god7hAPv8f0","time":"18:22","rs_id":"20554375","f_time":"2024.10.23. 18:22","itunes_pic":"Music115\/v4\/b2\/58\/27\/b258274e-9c1a-b989-46df-cc6f6506280c\/074646483220.jpg"},{"rs_artist":"BRUCE SPRINGSTEEN","rs_track":"My Hometown","rs_youtube_id":"KZ3BJYx43y0","time":"18:17","rs_id":"20554209","f_time":"2024.10.23. 18:17","itunes_pic":"Music118\/v4\/63\/76\/86\/6376864c-eee4-14f2-ad64-28c1b5aab8e9\/886447357644.jpg"},{"rs_artist":"SIMPLY RED","rs_track":"Stars","rs_youtube_id":"izOdvBmTDh0","time":"18:13","rs_id":"20554094","f_time":"2024.10.23. 18:13","itunes_pic":"Music\/d2\/cb\/6d\/mzi.tfyftdnu.jpg"},{"rs_artist":"QUEEN","rs_track":"Bicycle Race","rs_youtube_id":"xt0V0_1MS0Q","time":"18:07","rs_id":"20553881","f_time":"2024.10.23. 18:07","itunes_pic":"Music115\/v4\/4d\/08\/2a\/4d082a9e-7898-1aa1-a02f-339810058d9e\/14DMGIM05632.rgb.jpg"},{"rs_artist":"MICHAEL JACKSON","rs_track":"Billie Jean","rs_youtube_id":"Zi_XLOBDo_Y","time":"18:02","rs_id":"20553717","f_time":"2024.10.23. 18:02","itunes_pic":"Music125\/v4\/3d\/9d\/38\/3d9d3811-71f0-3a0e-1ada-3004e56ff852\/827969428726.jpg"},{"rs_artist":"MEAT LOAF","rs_track":"I'd Do Anything For Love (But I Won't Do That)","rs_youtube_id":"9X_ViIPA-Gc","time":"17:48","rs_id":"20553283","f_time":"2024.10.23. 17:48","itunes_pic":"Music128\/v4\/7e\/78\/40\/7e78407b-dc70-f873-9ce7-30f56d0d7905\/00602547046062.rgb.jpg"},{"rs_artist":"ABBA","rs_track":"S.O.S.","rs_youtube_id":"cvChjHcABPA","time":"17:45","rs_id":"20553181","f_time":"2024.10.23. 17:45","itunes_pic":"Music115\/v4\/60\/f8\/a6\/60f8a6bc-e875-238d-f2f8-f34a6034e6d2\/14UMGIM07615.rgb.jpg"},{"rs_artist":"PET SHOP BOYS","rs_track":"Always On My Mind","rs_youtube_id":"wDe60CbIagg","time":"17:39","rs_id":"20552972","f_time":"2024.10.23. 17:39","itunes_pic":"Music118\/v4\/47\/75\/a0\/4775a000-535a-181d-c231-a253b7ea6414\/094637594551.jpg"},{"rs_artist":"WHITESNAKE","rs_track":"Here I Go Again","rs_youtube_id":"WyF8RHM1OCg","time":"17:35","rs_id":"20552855","f_time":"2024.10.23. 17:35","itunes_pic":"Music125\/v4\/c2\/69\/53\/c2695381-d8b1-d122-0bef-be8663c848f8\/603497864980.jpg"},{"rs_artist":"TEARS FOR FEARS","rs_track":"Everybody Wants To Rule The World","rs_youtube_id":"aGCdLKXNF3w","time":"17:20","rs_id":"20552382","f_time":"2024.10.23. 17:20","itunes_pic":"Music125\/v4\/3c\/38\/fc\/3c38fcab-3855-c95c-6c07-6fa62db88a35\/14UMGIM34762.rgb.jpg"},{"rs_artist":"BEE GEES","rs_track":"More Than A Woman","rs_youtube_id":"uQ9_MwZIaoc","time":"17:15","rs_id":"20552228","f_time":"2024.10.23. 17:15","itunes_pic":"Music123\/v4\/94\/a7\/5f\/94a75fd1-17da-3a38-42dc-c5e35bf56046\/16UMGIM86639.rgb.jpg"},{"rs_artist":"ALANNAH MYLES","rs_track":"Black Velvet","rs_youtube_id":"tT4d1LQy4es","time":"17:09","rs_id":"20552019","f_time":"2024.10.23. 17:09","itunes_pic":"Music114\/v4\/2b\/48\/9b\/2b489bc2-92ba-a33b-ec8d-b07c596567a9\/mzi.aoxrflhk.jpg"},{"rs_artist":"WHITNEY HOUSTON","rs_track":"How Will I Know","rs_youtube_id":"m3-hY-hlhBg","time":"17:04","rs_id":"20551860","f_time":"2024.10.23. 17:04","itunes_pic":"Features115\/v4\/57\/ab\/ee\/57abee5e-6e30-eaaa-6d9c-e4f2ec360b72\/dj.tqbekvrp.jpg"},{"rs_artist":"TEN SHARP","rs_track":"You","rs_youtube_id":"SZQpVX8RIZY","time":"16:50","rs_id":"20551449","f_time":"2024.10.23. 16:50","itunes_pic":"Music\/52\/d5\/b8\/mzi.xakoqrxo.jpg"},{"rs_artist":"KISS","rs_track":"I Was Made For Loving You","rs_youtube_id":"ZhIsAZO5gl0","time":"16:43","rs_id":"20551218","f_time":"2024.10.23. 16:43","itunes_pic":"Music122\/v4\/92\/7f\/5c\/927f5c6f-e24a-8db5-e165-38d8b9314d8d\/14UMGIM16041.rgb.jpg"},{"rs_artist":"WHAM!","rs_track":"Club Tropicana","rs_youtube_id":"WYX0sjP6Za8","time":"16:39","rs_id":"20551075","f_time":"2024.10.23. 16:39","itunes_pic":"Music71\/v4\/5e\/9c\/3a\/5e9c3aec-3e54-69e0-f11f-78b2236cff2f\/886443224346.jpg"},{"rs_artist":"U2","rs_track":"Pride (In The Name Of Love)","rs_youtube_id":"LHcP4MWABGY","time":"16:35","rs_id":"20550952","f_time":"2024.10.23. 16:35","itunes_pic":"Music125\/v4\/dc\/6a\/c0\/dc6ac045-9bc7-be58-0a98-6932aa567343\/17UMGIM95505.rgb.jpg"},{"rs_artist":"ELTON JOHN","rs_track":"Your Song","rs_youtube_id":"GlPlfCy1urI","time":"16:21","rs_id":"20550518","f_time":"2024.10.23. 16:21","itunes_pic":"Music125\/v4\/9b\/30\/4c\/9b304cad-7427-b463-6bf7-8c1cf4fae484\/078636931920.jpg"},{"rs_artist":"KING","rs_track":"Love And Pride","rs_youtube_id":"UjyLp4X9dPU","time":"16:17","rs_id":"20550384","f_time":"2024.10.23. 16:17","itunes_pic":"Music124\/v4\/4d\/b6\/59\/4db65950-aced-877d-784a-c8c3b84cd3bf\/mzi.zrknhvlj.jpg"},{"rs_artist":"CHER","rs_track":"Believe","rs_youtube_id":"nZXRV4MezEw","time":"16:13","rs_id":"20550254","f_time":"2024.10.23. 16:13","itunes_pic":"Music123\/v4\/eb\/f9\/f5\/ebf9f545-4dd2-e407-0e4f-0fb9112c6fb8\/cover.jpg"},{"rs_artist":"KENNY LOGGINS","rs_track":"Footloose","rs_youtube_id":"ltrMfT4Qz5Y","time":"16:09","rs_id":"20550108","f_time":"2024.10.23. 16:09","itunes_pic":"Music124\/v4\/cf\/ea\/1e\/cfea1eda-337a-098b-060d-7d55bad1ff57\/mzm.wnowqorp.jpg"},{"rs_artist":"TRACEY ULLMAN","rs_track":"Breakaway","rs_youtube_id":"FiwopPbHGts","time":"16:05","rs_id":"20549999","f_time":"2024.10.23. 16:05","itunes_pic":""},{"rs_artist":"DEAD OR ALIVE","rs_track":"You Spin Me Round (Like A Record)","rs_youtube_id":"PGNiXGX2nLU","time":"16:02","rs_id":"20549889","f_time":"2024.10.23. 16:02","itunes_pic":"Music124\/v4\/ed\/19\/9e\/ed199ee3-cffc-5788-5731-d581a15e3285\/SFULT2.jpg"},{"rs_artist":"SANDRA","rs_track":"(I'll Never Be) Maria Magdalena","rs_youtube_id":"4jjzu1Z2RZc","time":"15:48","rs_id":"20549445","f_time":"2024.10.23. 15:48","itunes_pic":"Music114\/v4\/09\/cd\/b2\/09cdb25f-9da7-a113-e3bb-014197fa3d94\/13UABIM51736.rgb.jpg"},{"rs_artist":"BRUCE SPRINGSTEEN","rs_track":"The River","rs_youtube_id":"lc6F47Z6PI4","time":"15:43","rs_id":"20549281","f_time":"2024.10.23. 15:43","itunes_pic":"Music3\/v4\/a6\/a6\/53\/a6a65331-d20b-53b5-766a-0c79c78f1e73\/886445412307.jpg"},{"rs_artist":"DOE MAAR","rs_track":"Smoorverliefd","rs_youtube_id":"RpjAKwrWmLo","time":"15:40","rs_id":"20549167","f_time":"2024.10.23. 15:40","itunes_pic":"Music122\/v4\/2a\/4a\/e6\/2a4ae63d-ada7-fa57-6f16-02eebcf72f95\/18UMGIM29770.rgb.jpg"},{"rs_artist":"MR. BIG","rs_track":"To Be With You","rs_youtube_id":"L6-uJLteKek","time":"15:36","rs_id":"20549062","f_time":"2024.10.23. 15:36","itunes_pic":"Music115\/v4\/90\/68\/b6\/9068b687-ddd4-3bda-3aa0-9e40735580e5\/4897012132555.jpg"},{"rs_artist":"COMMUNARDS","rs_track":"Don't Leave Me This Way","rs_youtube_id":"1RHBAd5YUR8","time":"15:32","rs_id":"20548920","f_time":"2024.10.23. 15:32","itunes_pic":"Music118\/v4\/8d\/8e\/a3\/8d8ea397-575f-a3b2-32e4-4501cb1729aa\/639842824729.jpg"},{"rs_artist":"GENESIS","rs_track":"Follow You, Follow Me","rs_youtube_id":"DyDRXbP1MaY","time":"15:21","rs_id":"20548557","f_time":"2024.10.23. 15:21","itunes_pic":"Music\/2f\/5e\/61\/mzi.fornxdla.jpg"},{"rs_artist":"TAYLOR DAYNE","rs_track":"Tell It To My Heart","rs_youtube_id":"Ud6sU3AclT4","time":"15:17","rs_id":"20548428","f_time":"2024.10.23. 15:17","itunes_pic":"Music115\/v4\/b9\/ce\/21\/b9ce218d-fa19-3645-1506-f4d862ceae67\/mzi.eumpbjlo.jpg"},{"rs_artist":"ERIC CLAPTON","rs_track":"Tears In Heaven","rs_youtube_id":"JxPj3GAYYZ0","time":"15:13","rs_id":"20548277","f_time":"2024.10.23. 15:13","itunes_pic":"Music112\/v4\/b4\/a8\/99\/b4a89922-4b67-104e-f85c-d6d478303e65\/93624755364.jpg"},{"rs_artist":"BANGLES","rs_track":"Walk Like An Egyptian","rs_youtube_id":"Cv6tuzHUuuk","time":"15:10","rs_id":"20548174","f_time":"2024.10.23. 15:10","itunes_pic":"Music124\/v4\/b2\/2a\/57\/b22a5707-86ae-2719-e661-b7c4a91773c5\/mzi.gizvcfrx.jpg"},{"rs_artist":"FRANKIE VALLI","rs_track":"Grease","rs_youtube_id":"ZC7v2gFsCz0","time":"15:07","rs_id":"20548061","f_time":"2024.10.23. 15:07","itunes_pic":"Music115\/v4\/a0\/b6\/98\/a0b6983b-3e5b-0a42-3d04-308425815922\/s06.tapekocb.jpg"},{"rs_artist":"TINA TURNER","rs_track":"We Don't Need Another Hero","rs_youtube_id":"Gcm-tOGiva0","time":"15:02","rs_id":"20547905","f_time":"2024.10.23. 15:02","itunes_pic":"Features125\/v4\/91\/a9\/3d\/91a93dd8-b591-6aab-21b7-da5669f61a9c\/dj.glozlwoq.jpg"},{"rs_artist":"MICHAEL JACKSON","rs_track":"Man In The Mirror","rs_youtube_id":"PivWY9wn5ps","time":"14:49","rs_id":"20547505","f_time":"2024.10.23. 14:49","itunes_pic":"Music125\/v4\/3d\/9d\/38\/3d9d3811-71f0-3a0e-1ada-3004e56ff852\/827969428726.jpg"},{"rs_artist":"KYLIE MINOGUE","rs_track":"The Locomotion","rs_youtube_id":"POWsFzSFLCE","time":"14:46","rs_id":"20547398","f_time":"2024.10.23. 14:46","itunes_pic":"Music125\/v4\/d0\/9e\/fa\/d09efa3b-f49a-f456-d26d-5a1cca158344\/00094636459752.rgb.jpg"},{"rs_artist":"SOUL ASYLUM","rs_track":"Runaway Train","rs_youtube_id":"NRtvqT_wMeY","time":"14:42","rs_id":"20547258","f_time":"2024.10.23. 14:42","itunes_pic":"Music\/99\/61\/07\/mzi.wzrulphk.jpg"},{"rs_artist":"SISTER SLEDGE","rs_track":"Lost In Music","rs_youtube_id":"43qB9FpfCR8","time":"14:38","rs_id":"20547107","f_time":"2024.10.23. 14:38","itunes_pic":"Music\/da\/e8\/56\/mzi.ptvoczcg.jpg"},{"rs_artist":"SIMPLY RED","rs_track":"Holding Back The Years","rs_youtube_id":"yG07WSu7Q9w","time":"14:34","rs_id":"20546969","f_time":"2024.10.23. 14:34","itunes_pic":"Music114\/v4\/a9\/67\/39\/a9673982-c12f-7756-62ef-93e47f036e1e\/mzi.vykvsspo.jpg"},{"rs_artist":"ABBA","rs_track":"Chiquitita","rs_youtube_id":"p4QqMKe3rwY","time":"14:21","rs_id":"20546573","f_time":"2024.10.23. 14:21","itunes_pic":"Music115\/v4\/60\/f8\/a6\/60f8a6bc-e875-238d-f2f8-f34a6034e6d2\/14UMGIM07615.rgb.jpg"},{"rs_artist":"SADE","rs_track":"The Sweetest Taboo","rs_youtube_id":"kcPc18SG6uA","time":"14:18","rs_id":"20546444","f_time":"2024.10.23. 14:18","itunes_pic":"Music115\/v4\/5f\/ad\/2a\/5fad2aca-d998-701d-7b27-c074339d5fd0\/886972262628.jpg"},{"rs_artist":"ROXETTE","rs_track":"Joyride","rs_youtube_id":"xCorJG9mubk","time":"14:14","rs_id":"20546304","f_time":"2024.10.23. 14:14","itunes_pic":"Music114\/v4\/5c\/ef\/d7\/5cefd760-1260-4081-621a-85db2355e13a\/dj.gmqdvhoe.jpg"},{"rs_artist":"GERRY RAFFERTY","rs_track":"Baker Street","rs_youtube_id":"Fo6aKnRnBxM","time":"14:08","rs_id":"20546127","f_time":"2024.10.23. 14:08","itunes_pic":"Music125\/v4\/d8\/a3\/a0\/d8a3a079-d358-2a95-9ece-9885c448c486\/dj.qbsugeyr.jpg"},{"rs_artist":"PRINCE","rs_track":"When Doves Cry","rs_youtube_id":"UG3VcCAlUgE","time":"14:05","rs_id":"20546001","f_time":"2024.10.23. 14:05","itunes_pic":"Music115\/v4\/c1\/b6\/79\/c1b679f5-d59d-1b3e-62ab-514de20f06c6\/093624912002.jpg"},{"rs_artist":"BILLY JOEL","rs_track":"Honesty","rs_youtube_id":"SuFScoO4tb0","time":"13:52","rs_id":"20545633","f_time":"2024.10.23. 13:52","itunes_pic":"Music125\/v4\/f0\/7a\/54\/f07a54ab-3ebc-6813-e515-86200b8138fc\/dj.uthntyfe.jpg"},{"rs_artist":"LIGHTHOUSE FAMILY","rs_track":"High","rs_youtube_id":"taOL5HJdx1A","time":"13:49","rs_id":"20545521","f_time":"2024.10.23. 13:49","itunes_pic":"Music124\/v4\/cb\/fe\/90\/cbfe90c7-e9ae-7f42-74a3-f79079dd2f54\/00044006544823.rgb.jpg"},{"rs_artist":"MELISSA ETHERIDGE","rs_track":"Like The Way I Do","rs_youtube_id":"p07GhDsZgz4","time":"13:46","rs_id":"20545396","f_time":"2024.10.23. 13:46","itunes_pic":"Music115\/v4\/20\/ef\/d3\/20efd3e9-9733-11e2-7ffe-acad1d5f9660\/00602557202854.rgb.jpg"},{"rs_artist":"BONEY M","rs_track":"Daddy Cool","rs_youtube_id":"FYGTT7YhywA","time":"13:43","rs_id":"20545289","f_time":"2024.10.23. 13:43","itunes_pic":"Music115\/v4\/b7\/86\/45\/b786452a-a723-eaed-8170-cdc261367eb7\/886443575578.jpg"},{"rs_artist":"MIKE OLDFIELD","rs_track":"Moonlight Shadow","rs_youtube_id":"e80qhyovOnA","time":"13:39","rs_id":"20545171","f_time":"2024.10.23. 13:39","itunes_pic":"Music115\/v4\/d9\/24\/3b\/d9243b7b-3274-8142-8771-00133e3e587f\/00602527065489.rgb.jpg"},{"rs_artist":"BACKSTREET BOYS","rs_track":"I Want It That Way","rs_youtube_id":"4fndeDfaWCg","time":"13:35","rs_id":"20545038","f_time":"2024.10.23. 13:35","itunes_pic":"Music114\/v4\/59\/00\/53\/59005338-772d-2dd7-e2ff-674484629337\/012414158925.jpg"},{"rs_artist":"MEN AT WORK","rs_track":"Down Under","rs_youtube_id":"XfR9iY5y94s","time":"13:32","rs_id":"20544923","f_time":"2024.10.23. 13:32","itunes_pic":"Music115\/v4\/c0\/69\/00\/c0690034-99df-60e5-0169-437adff1a06d\/mzi.dsehorsv.jpg"},{"rs_artist":"UB40","rs_track":"Where Did I Go Wrong","rs_youtube_id":"7B3g1ovVQzc","time":"13:22","rs_id":"20544592","f_time":"2024.10.23. 13:22","itunes_pic":"Music4\/v4\/8b\/72\/66\/8b7266ad-174c-ec15-1d75-c014e79a883b\/00077778638858.jpg"},{"rs_artist":"SUPERTRAMP","rs_track":"Breakfast In America","rs_youtube_id":"3YQb-0P320s","time":"13:19","rs_id":"20544497","f_time":"2024.10.23. 13:19","itunes_pic":"Music125\/v4\/09\/95\/b3\/0995b3e6-1dfd-7eed-e4fc-3ec7594c8fde\/06UMGIM10542.rgb.jpg"},{"rs_artist":"MATTHEW WILDER","rs_track":"Break My Stride","rs_youtube_id":"B4c_SkROzzo","time":"13:17","rs_id":"20544421","f_time":"2024.10.23. 13:17","itunes_pic":"Music115\/v4\/c9\/c0\/d1\/c9c0d17d-389f-50ad-0475-8ef1e70f217a\/mzi.nuojehpg.jpg"},{"rs_artist":"SINEAD O'CONNOR","rs_track":"Nothing Compares 2 U","rs_youtube_id":"0-EF60neguk","time":"13:13","rs_id":"20544297","f_time":"2024.10.23. 13:13","itunes_pic":"Music122\/v4\/76\/43\/92\/764392cc-de5e-eadd-8ccc-ba0e3ec04401\/5054526647565.png"},{"rs_artist":"EL DEBARGE","rs_track":"Who's Johnny","rs_youtube_id":"yA9WhYnsD_4","time":"13:09","rs_id":"20544159","f_time":"2024.10.23. 13:09","itunes_pic":"Music128\/v4\/ad\/3d\/ff\/ad3dffd8-b8d4-a9a0-f221-9d3fc3a2a2f6\/00602577177538.rgb.jpg"},{"rs_artist":"DOOBIE BROTHERS","rs_track":"What A Fool Believes","rs_youtube_id":"qKYQNtF11eg","time":"13:06","rs_id":"20544056","f_time":"2024.10.23. 13:06","itunes_pic":"Music124\/v4\/69\/92\/94\/6992941f-42a9-265d-1471-3e8d319ea697\/mzi.yuwsvyfh.jpg"},{"rs_artist":"FLEETWOOD MAC","rs_track":"Everywhere","rs_youtube_id":"YF1R0hc5Q2I","time":"13:03","rs_id":"20543949","f_time":"2024.10.23. 13:03","itunes_pic":"Music124\/v4\/7d\/5b\/04\/7d5b0401-b944-b628-8eb2-d0cb49fb6ca5\/603497925599.jpg"},{"rs_artist":"RICK JAMES","rs_track":"Superfreak","rs_youtube_id":"QYHxGBH6o4M","time":"12:49","rs_id":"20543530","f_time":"2024.10.23. 12:49","itunes_pic":"Music125\/v4\/22\/60\/6c\/22606cd1-40fc-3b1e-fbb0-65dcf102bf08\/06UMGIM02155.rgb.jpg"},{"rs_artist":"PAUL YOUNG","rs_track":"Everytime You Go Away","rs_youtube_id":"nfk6sCzRTbM","time":"12:45","rs_id":"20543401","f_time":"2024.10.23. 12:45","itunes_pic":"Music\/41\/ad\/b3\/mzi.mjnacoxa.jpg"},{"rs_artist":"WHITNEY HOUSTON","rs_track":"I Wanna Dance With Somebody (Who Loves Me)","rs_youtube_id":"eH3giaIzONA","time":"12:41","rs_id":"20543247","f_time":"2024.10.23. 12:41","itunes_pic":"Music115\/v4\/86\/b5\/25\/86b525b1-bff1-4bf6-6112-531251b3d672\/dj.hthdmusj.jpg"},{"rs_artist":"ZZ TOP","rs_track":"Gimme All Your Lovin'","rs_youtube_id":"Ae829mFAGGE","time":"12:38","rs_id":"20543133","f_time":"2024.10.23. 12:38","itunes_pic":"Music126\/v4\/8e\/c8\/cf\/8ec8cfbe-317c-02a3-4e69-ae343cafef39\/0075992684668.jpg"},{"rs_artist":"DIANA ROSS","rs_track":"I'm Coming Out","rs_youtube_id":"F-mjl63e0ms","time":"12:34","rs_id":"20543010","f_time":"2024.10.23. 12:34","itunes_pic":"Music124\/v4\/4b\/68\/94\/4b68944b-e875-5729-e97f-c781fc9e0c1e\/06UMGIM11291.rgb.jpg"},{"rs_artist":"SPANDAU BALLET","rs_track":"Gold","rs_youtube_id":"ntG50eXbBtc","time":"12:31","rs_id":"20542887","f_time":"2024.10.23. 12:31","itunes_pic":"Music125\/v4\/12\/f3\/f3\/12f3f32b-5164-6bc6-ee55-1c6ff918cc6d\/dj.yblscykq.jpg"},{"rs_artist":"BOB MARLEY & THE WAILERS","rs_track":"Could You Be Loved","rs_youtube_id":"1ti2YCFgCoI","time":"12:20","rs_id":"20542548","f_time":"2024.10.23. 12:20","itunes_pic":"Music113\/v4\/ea\/20\/06\/ea2006f9-7512-cf9c-7b44-78116156875e\/12UMGIM14712.rgb.jpg"},{"rs_artist":"SOFT CELL","rs_track":"Tainted Love","rs_youtube_id":"XZVpR3Pk-r8","time":"12:17","rs_id":"20542444","f_time":"2024.10.23. 12:17","itunes_pic":"Music114\/v4\/e8\/31\/2a\/e8312a55-26d0-afbf-f70c-8f260fc090be\/06UMGIM16301.rgb.jpg"},{"rs_artist":"ALPHAVILLE","rs_track":"Forever Young","rs_youtube_id":"t1TcDHrkQYg","time":"12:14","rs_id":"20542323","f_time":"2024.10.23. 12:14","itunes_pic":"Music125\/v4\/c9\/f5\/e6\/c9f5e66e-8ab1-5c75-dbe7-7670f9204776\/s06.emtrcgpz.jpg"},{"rs_artist":"MADONNA","rs_track":"Holiday","rs_youtube_id":"h4bP9tj_0Zk","time":"12:10","rs_id":"20542187","f_time":"2024.10.23. 12:10","itunes_pic":"Music\/y2005\/m09\/d19\/h20\/mzi.ykiinwgl.jpg"},{"rs_artist":"TERENCE TRENT D'ARBY","rs_track":"Sign Your Name","rs_youtube_id":"dluHzQhLcME","time":"12:06","rs_id":"20542066","f_time":"2024.10.23. 12:06","itunes_pic":"Music\/5d\/f3\/e8\/mzi.camavkpp.jpg"},{"rs_artist":"QUEEN","rs_track":"Another One Bites The Dust","rs_youtube_id":"rY0WxgSXdEE","time":"12:03","rs_id":"20541940","f_time":"2024.10.23. 12:03","itunes_pic":"Music115\/v4\/4d\/08\/2a\/4d082a9e-7898-1aa1-a02f-339810058d9e\/14DMGIM05632.rgb.jpg"},{"rs_artist":"ANOUK","rs_track":"R U Kiddin' Me","rs_youtube_id":"59GUpnJWYZw","time":"11:52","rs_id":"20541614","f_time":"2024.10.23. 11:52","itunes_pic":"Music\/v4\/1b\/49\/e3\/1b49e3c6-dd07-b8fa-f6a5-422f0bacc430\/00094636100654.jpg"},{"rs_artist":"DOE MAAR","rs_track":"Is Dit Alles","rs_youtube_id":"ZwOAR7SsUmc","time":"11:47","rs_id":"20541453","f_time":"2024.10.23. 11:47","itunes_pic":"Music\/31\/38\/98\/mzi.ukdyyxto.jpg"},{"rs_artist":"ROBERT CRAY BAND","rs_track":"Right Next Door","rs_youtube_id":"jP2EvSNHqh0","time":"11:43","rs_id":"20541324","f_time":"2024.10.23. 11:43","itunes_pic":"Music128\/v4\/c1\/38\/15\/c138152a-52c3-a1b3-c9d2-7cbb83bd3af4\/00602537845507.rgb.jpg"},{"rs_artist":"TAVARES","rs_track":"Heaven Must Be Missing An Angel","rs_youtube_id":"J123lM0RvzM","time":"11:40","rs_id":"20541211","f_time":"2024.10.23. 11:40","itunes_pic":"Music115\/v4\/d0\/1c\/25\/d01c258f-3dab-ed7b-08a2-2287ce23fcd4\/00724359374550.jpg"},{"rs_artist":"4 NON BLONDES","rs_track":"What's Up?","rs_youtube_id":"6NXnxTNIWkc","time":"11:36","rs_id":"20541082","f_time":"2024.10.23. 11:36","itunes_pic":"Music\/cd\/8b\/9a\/mzi.kimlabhg.jpg"},{"rs_artist":"PHIL COLLINS","rs_track":"Another Day In Paradise","rs_youtube_id":"Qt2mbGP6vFI","time":"11:33","rs_id":"20540975","f_time":"2024.10.23. 11:33","itunes_pic":"Music115\/v4\/1c\/83\/f9\/1c83f950-aa62-aeb7-f561-21d9541514ba\/dj.wxggooob.jpg"},{"rs_artist":"JOHN MILES","rs_track":"Music","rs_youtube_id":"gb6XtyFNawM","time":"11:21","rs_id":"20540599","f_time":"2024.10.23. 11:21","itunes_pic":"Video111\/v4\/9c\/44\/d6\/9c44d6fd-df10-b702-65b1-d553c459201c\/pr_source.lsr\/100x100bb.jpg"},{"rs_artist":"JERMAINE JACKSON & PIA ZADORA","rs_track":"When The Rain Begins To Fall","rs_youtube_id":"aahViYznVTQ","time":"11:17","rs_id":"20540467","f_time":"2024.10.23. 11:17","itunes_pic":"Music126\/v4\/c7\/3d\/66\/c73d6665-8581-cca2-646c-51be6a40e888\/886445548891.jpg"},{"rs_artist":"MADNESS","rs_track":"Our House","rs_youtube_id":"KwIe_sjKeAY","time":"11:14","rs_id":"20540380","f_time":"2024.10.23. 11:14","itunes_pic":"Music128\/v4\/4d\/c7\/2a\/4dc72acc-c29f-6692-aa7a-750c63d03085\/00720642514528.rgb.jpg"},{"rs_artist":"ELTON JOHN","rs_track":"Circle Of Life","rs_youtube_id":"IwH9YvhPN7c","time":"11:09","rs_id":"20540225","f_time":"2024.10.23. 11:09","itunes_pic":"Music116\/v4\/ce\/80\/89\/ce808921-d594-fa7f-03e8-adcc92a69de8\/06PNDIM00020.rgb.jpg"},{"rs_artist":"ABBA","rs_track":"Take A Chance On Me","rs_youtube_id":"-crgQGdpZR0","time":"11:05","rs_id":"20540082","f_time":"2024.10.23. 11:05","itunes_pic":"Music115\/v4\/60\/f8\/a6\/60f8a6bc-e875-238d-f2f8-f34a6034e6d2\/14UMGIM07615.rgb.jpg"},{"rs_artist":"TINA TURNER","rs_track":"What's Love Got To Do With It","rs_youtube_id":"oGpFcHTxjZs","time":"11:02","rs_id":"20539953","f_time":"2024.10.23. 11:02","itunes_pic":"Music115\/v4\/94\/f4\/88\/94f48860-5756-665f-329b-968b6264fe03\/825646337910.jpg"},{"rs_artist":"BILL WITHERS","rs_track":"Lovely Day","rs_youtube_id":"bEeaS6fuUoA","time":"10:50","rs_id":"20539593","f_time":"2024.10.23. 10:50","itunes_pic":"Music125\/v4\/3a\/93\/40\/3a9340a1-73f7-5bbb-86a2-15a4ba20acea\/884977735840.jpg"},{"rs_artist":"PRINCE & THE REVOLUTION","rs_track":"Purple Rain","rs_youtube_id":"bm03wqLY3Nc","time":"10:45","rs_id":"20539437","f_time":"2024.10.23. 10:45","itunes_pic":"Video221\/v4\/05\/f4\/81\/05f48137-b57b-1bc6-865c-7bb3c02d4fb5\/8541e82c-e9e0-479f-bcaf-040bbc148875_Purple_Rain_4K_V_DD_KA_TT_2000x3000_300dpi_EN-p3.lsr"},{"rs_artist":"LIONEL RICHIE","rs_track":"My Destiny","rs_youtube_id":"1AFN4dn09oM","time":"10:42","rs_id":"20539310","f_time":"2024.10.23. 10:42","itunes_pic":"Music122\/v4\/d0\/4f\/9b\/d04f9b9f-c06a-76ec-1c6e-2bca44142518\/06UMGIM17674.rgb.jpg"},{"rs_artist":"DAVID BOWIE","rs_track":"This Is Not America","rs_youtube_id":"nsMUxdZGgWI","time":"10:38","rs_id":"20539189","f_time":"2024.10.23. 10:38","itunes_pic":"Features115\/v4\/fc\/65\/98\/fc6598f9-706b-48a2-dc37-9854f703b21e\/dj.xnockfyi.jpg"},{"rs_artist":"NEIL DIAMOND","rs_track":"Sweet Caroline","rs_youtube_id":"ty1dwBCR6D0","time":"10:35","rs_id":"20539086","f_time":"2024.10.23. 10:35","itunes_pic":"Music\/1d\/06\/9b\/mzi.benjyygo.jpg"},{"rs_artist":"HUMAN LEAGUE","rs_track":"Don't You Want Me","rs_youtube_id":"uPudE8nDog0","time":"10:31","rs_id":"20538969","f_time":"2024.10.23. 10:31","itunes_pic":"Music124\/v4\/b2\/ab\/29\/b2ab29c9-add0-65cf-070e-933cca1daefa\/13UABIM56759.rgb.jpg"},{"rs_artist":"YOUSSOU N'DOUR & NENEH CHERRY","rs_track":"7 Seconds","rs_youtube_id":"wqCpjFMvz-k","time":"10:21","rs_id":"20538636","f_time":"2024.10.23. 10:21","itunes_pic":"Music124\/v4\/24\/dd\/21\/24dd21dc-9477-d8f6-4341-ef55d80a1567\/mzi.jcefhylw.jpg"},{"rs_artist":"REAL THING","rs_track":"You To Me Are Everything","rs_youtube_id":"_aNxQ3xICqU","time":"10:18","rs_id":"20538513","f_time":"2024.10.23. 10:18","itunes_pic":"Music124\/v4\/c5\/ee\/b2\/c5eeb291-ec8b-b1df-66e1-00c966dd2d55\/mzi.yssniwyq.jpg"},{"rs_artist":"ROXETTE","rs_track":"The Look","rs_youtube_id":"LlVI7ZNiFlI","time":"10:14","rs_id":"20538387","f_time":"2024.10.23. 10:14","itunes_pic":"Music114\/v4\/5c\/ef\/d7\/5cefd760-1260-4081-621a-85db2355e13a\/dj.gmqdvhoe.jpg"},{"rs_artist":"ROBBIE WILLIAMS","rs_track":"She's The One","rs_youtube_id":"sVaRHJn_dgM","time":"10:10","rs_id":"20538250","f_time":"2024.10.23. 10:10","itunes_pic":"Music113\/v4\/ef\/8d\/ec\/ef8dec37-0ed0-7085-2780-80da0f93dfb6\/14ULAIM00713.rgb.jpg"},{"rs_artist":"BEE GEES","rs_track":"You Should Be Dancing","rs_youtube_id":"_JoZS6LgqYI","time":"10:06","rs_id":"20538111","f_time":"2024.10.23. 10:06","itunes_pic":"Music123\/v4\/94\/a7\/5f\/94a75fd1-17da-3a38-42dc-c5e35bf56046\/16UMGIM86639.rgb.jpg"},{"rs_artist":"MICHAEL JACKSON","rs_track":"Bad","rs_youtube_id":"dsUXAEzaC3Q","time":"10:02","rs_id":"20537973","f_time":"2024.10.23. 10:02","itunes_pic":"Music125\/v4\/3d\/9d\/38\/3d9d3811-71f0-3a0e-1ada-3004e56ff852\/827969428726.jpg"},{"rs_artist":"CLOUSEAU","rs_track":"Domino","rs_youtube_id":"wU6oT7H8eWY","time":"09:50","rs_id":"20537630","f_time":"2024.10.23. 09:50","itunes_pic":"Music\/52\/c7\/3f\/mzi.jilpzyyb.jpg"},{"rs_artist":"WHAM!","rs_track":"I'm Your Man","rs_youtube_id":"6W0d9xMhZbo","time":"09:46","rs_id":"20537468","f_time":"2024.10.23. 09:46","itunes_pic":"Music\/f8\/c2\/15\/mzi.jfusioan.jpg"},{"rs_artist":"MICHEL DELPECH","rs_track":"Pour Un Flirt","rs_youtube_id":"Rc90o31VKyk","time":"09:42","rs_id":"20537354","f_time":"2024.10.23. 09:42","itunes_pic":"Music124\/v4\/9f\/19\/33\/9f19331e-970f-f086-48a0-e4a710133ebb\/00602498146927.rgb.jpg"},{"rs_artist":"SPICE GIRLS","rs_track":"2 Become 1","rs_youtube_id":"FA5jsa1lR9c","time":"09:37","rs_id":"20537171","f_time":"2024.10.23. 09:37","itunes_pic":"Music116\/v4\/c0\/90\/ca\/c090caa0-718d-9646-15c5-bd6741ba8491\/13UABIM59225.rgb.jpg"},{"rs_artist":"DAN HARTMAN","rs_track":"Relight My Fire","rs_youtube_id":"S7Plis5xFBg","time":"09:33","rs_id":"20537059","f_time":"2024.10.23. 09:33","itunes_pic":"Music125\/v4\/ab\/9f\/f7\/ab9ff7f0-12be-d509-e293-3b73732d4dbe\/886447016053.jpg"},{"rs_artist":"INCOGNITO & JOCELYN BROWN","rs_track":"Always There","rs_youtube_id":"X6JM8iagb8o","time":"09:21","rs_id":"20536678","f_time":"2024.10.23. 09:21","itunes_pic":""},{"rs_artist":"FOREIGNER","rs_track":"I Want To Know What Love Is","rs_youtube_id":"r3Pr1_v7hsw","time":"09:18","rs_id":"20536570","f_time":"2024.10.23. 09:18","itunes_pic":"Music125\/v4\/af\/7b\/a2\/af7ba295-c0c0-ba8d-17da-5cc52959a602\/mzi.ykpmzuxm.jpg"},{"rs_artist":"THE POLICE","rs_track":"Message In A Bottle","rs_youtube_id":"MbXWrmQW-OE","time":"09:13","rs_id":"20536427","f_time":"2024.10.23. 09:13","itunes_pic":"Music211\/v4\/42\/b7\/db\/42b7dbe1-d13f-c600-5b78-daa57c5d0f08\/06UMGIM50761.rgb.jpg"},{"rs_artist":"HADDAWAY","rs_track":"What Is Love","rs_youtube_id":"HEXWRTEbj1I","time":"09:08","rs_id":"20536255","f_time":"2024.10.23. 09:08","itunes_pic":"Music\/v4\/44\/86\/6f\/44866fac-f07a-0898-5ef2-32fd7ee29878\/Cover.jpg"},{"rs_artist":"TOTO","rs_track":"Stop Loving You","rs_youtube_id":"bYr3OJOXk60","time":"09:04","rs_id":"20536121","f_time":"2024.10.23. 09:04","itunes_pic":"Features114\/v4\/a9\/4c\/42\/a94c42eb-59ef-fe37-be31-8c4a962da01c\/dj.jpjirwkd.jpg"},{"rs_artist":"QUEEN","rs_track":"Crazy Little Thing Called Love","rs_youtube_id":"zO6D_BAuYCI","time":"08:51","rs_id":"20535731","f_time":"2024.10.23. 08:51","itunes_pic":"Music115\/v4\/4d\/08\/2a\/4d082a9e-7898-1aa1-a02f-339810058d9e\/14DMGIM05632.rgb.jpg"},{"rs_artist":"TRACY CHAPMAN","rs_track":"Fast Car","rs_youtube_id":"DwrHwZyFN7M","time":"08:41","rs_id":"20535405","f_time":"2024.10.23. 08:41","itunes_pic":"Music126\/v4\/b8\/c4\/31\/b8c431e9-a67d-3917-72e5-be9f5a1ebc46\/075596077460.jpg"},{"rs_artist":"POINTER SISTERS","rs_track":"Jump (For My Love)","rs_youtube_id":"uyTVyCp7xrw","time":"08:37","rs_id":"20535263","f_time":"2024.10.23. 08:37","itunes_pic":"Features114\/v4\/64\/13\/db\/6413db84-4325-81e8-df43-ac7567389520\/dj.zvelubll.jpg"},{"rs_artist":"ACDA & DE MUNNIK","rs_track":"Het Regent Zonnestralen","rs_youtube_id":"dZkbhA1NcTM","time":"08:18","rs_id":"20534629","f_time":"2024.10.23. 08:18","itunes_pic":"Music221\/v4\/2f\/02\/9c\/2f029ccd-53b7-0e1b-f970-1b03ce3e16d9\/196872411775.jpg"},{"rs_artist":"BARRY WHITE","rs_track":"Let The Music Play","rs_youtube_id":"tfFjm-6cbu8","time":"08:14","rs_id":"20534502","f_time":"2024.10.23. 08:14","itunes_pic":"Music124\/v4\/c7\/3a\/27\/c73a27c0-cadd-2ba7-2976-9070bc233b47\/00602567825555.rgb.jpg"},{"rs_artist":"TEARS FOR FEARS","rs_track":"Shout","rs_youtube_id":"Ye7FKc1JQe4","time":"08:04","rs_id":"20534196","f_time":"2024.10.23. 08:04","itunes_pic":"Music125\/v4\/3c\/38\/fc\/3c38fcab-3855-c95c-6c07-6fa62db88a35\/14UMGIM34762.rgb.jpg"},{"rs_artist":"BOB MARLEY & THE WAILERS","rs_track":"Stir It Up","rs_youtube_id":"rf8GjhXvOjU","time":"07:51","rs_id":"20533792","f_time":"2024.10.23. 07:51","itunes_pic":"Music113\/v4\/ea\/20\/06\/ea2006f9-7512-cf9c-7b44-78116156875e\/12UMGIM14712.rgb.jpg"},{"rs_artist":"SURVIVOR","rs_track":"Burning Heart","rs_youtube_id":"Kc71KZG87X4","time":"07:42","rs_id":"20533499","f_time":"2024.10.23. 07:42","itunes_pic":"Features124\/v4\/3b\/26\/23\/3b26239a-c74c-b4f3-974c-11ed3591647f\/dj.bnjsuuki.jpg"},{"rs_artist":"A-HA","rs_track":"Take On Me","rs_youtube_id":"djV11Xbc914","time":"07:39","rs_id":"20533378","f_time":"2024.10.23. 07:39","itunes_pic":"Music124\/v4\/3e\/0a\/38\/3e0a38d9-b138-429a-61e1-aeac2fad3263\/mzi.iefykuuf.jpg"},{"rs_artist":"U2","rs_track":"Where The Streets Have No Name","rs_youtube_id":"GzZWSrr5wFI","time":"07:22","rs_id":"20532850","f_time":"2024.10.23. 07:22","itunes_pic":"Music115\/v4\/d9\/cd\/b2\/d9cdb23f-37a3-9c90-4bbf-e4b99c6b8228\/17UMGIM84937.rgb.jpg"},{"rs_artist":"CHAKA KHAN","rs_track":"I'm Every Woman","rs_youtube_id":"DVDCNmdi7QI","time":"07:16","rs_id":"20532645","f_time":"2024.10.23. 07:16","itunes_pic":"Music124\/v4\/5a\/45\/8c\/5a458cce-ffe2-2669-7abd-b9c5bd91898b\/mzi.cqwjyszs.jpg"},{"rs_artist":"BRUCE SPRINGSTEEN","rs_track":"Streets Of Philadelphia","rs_youtube_id":"4z2DtNW79sQ","time":"07:12","rs_id":"20532535","f_time":"2024.10.23. 07:12","itunes_pic":"Music125\/v4\/b2\/fd\/8e\/b2fd8ec2-3494-fd9a-b7ad-aacaacea8cde\/886447315088.jpg"},{"rs_artist":"TINA TURNER","rs_track":"The Best","rs_youtube_id":"GC5E8ie2pdM","time":"07:03","rs_id":"20532223","f_time":"2024.10.23. 07:03","itunes_pic":"Video126\/v4\/d8\/3c\/23\/d83c2384-c13a-3899-195f-eb8868987f90\/Giant_TinaTurnerSimplyTheBest_iTunes_Poster.png"},{"rs_artist":"PHIL COLLINS","rs_track":"You'll Be In My Heart","rs_youtube_id":"w0ZHlp6atUQ","time":"06:51","rs_id":"20531862","f_time":"2024.10.23. 06:51","itunes_pic":"Music126\/v4\/09\/ff\/d4\/09ffd48c-f525-ae2b-be96-b12696d83a49\/18UMGIM62087.rgb.jpg"},{"rs_artist":"JACKSONS","rs_track":"Blame It On The Boogie","rs_youtube_id":"nqxVMLVe62U","time":"06:48","rs_id":"20531756","f_time":"2024.10.23. 06:48","itunes_pic":"Music125\/v4\/3d\/9d\/38\/3d9d3811-71f0-3a0e-1ada-3004e56ff852\/827969428726.jpg"},{"rs_artist":"TALK TALK","rs_track":"It's My Life","rs_youtube_id":"cFH5JgyZK1I","time":"06:39","rs_id":"20531453","f_time":"2024.10.23. 06:39","itunes_pic":"Music111\/v4\/9b\/ab\/79\/9bab79d7-d814-3db9-5ff3-a8b8af0bc019\/724385573552.jpg"},{"rs_artist":"HET GOEDE DOEL","rs_track":"Belgi\u00eb","rs_youtube_id":"sT9LcvG9Uec","time":"06:36","rs_id":"20531337","f_time":"2024.10.23. 06:36","itunes_pic":"Music118\/v4\/ad\/d2\/23\/add223ec-6ab0-d7fb-9ccf-9b4b054bc4fa\/00602547368423.rgb.jpg"},{"rs_artist":"NARADA MICHAEL WALDEN","rs_track":"Gimme Gimme Gimme","rs_youtube_id":"OrnUuXiVgBc","time":"06:22","rs_id":"20530889","f_time":"2024.10.23. 06:22","itunes_pic":"Music\/y2005\/m03\/d14\/h21\/s06.rginrcqt.jpg"},{"rs_artist":"AEROSMITH","rs_track":"I Don't Want To Miss A Thing","rs_youtube_id":"JkK8g6FMEXE","time":"06:14","rs_id":"20530636","f_time":"2024.10.23. 06:14","itunes_pic":"Music115\/v4\/0a\/f1\/af\/0af1af45-7deb-3252-15e2-c1394b574d64\/mzi.lfxshysm.jpg"},{"rs_artist":"ABBA","rs_track":"Super Trouper","rs_youtube_id":"BshxCIjNEjY","time":"06:10","rs_id":"20530498","f_time":"2024.10.23. 06:10","itunes_pic":"Music115\/v4\/60\/f8\/a6\/60f8a6bc-e875-238d-f2f8-f34a6034e6d2\/14UMGIM07615.rgb.jpg"},{"rs_artist":"EURYTHMICS","rs_track":"Sweet Dreams (Are Made Of This)","rs_youtube_id":"qeMFqkcPYcg","time":"06:02","rs_id":"20530245","f_time":"2024.10.23. 06:02","itunes_pic":"Music115\/v4\/91\/dc\/dc\/91dcdcc0-0844-5257-e89c-fceba19673bc\/886449239580.jpg"},{"rs_artist":"ULTRAVOX","rs_track":"Dancing With Tears In My Eyes","rs_youtube_id":"PSQWUZ8a2Ho","time":"05:56","rs_id":"20530048","f_time":"2024.10.23. 05:56","itunes_pic":"Music112\/v4\/e6\/9e\/9c\/e69e9c57-b4a6-94ef-d679-f9014f8485e4\/0810098501170.png"},{"rs_artist":"OLETA ADAMS","rs_track":"Window Of Hope","rs_youtube_id":"xc68sRFZ650","time":"05:52","rs_id":"20529903","f_time":"2024.10.23. 05:52","itunes_pic":"Music128\/v4\/d9\/a4\/56\/d9a456be-2598-ff29-fbd0-ded5e1b86af7\/00731455884425.rgb.jpg"},{"rs_artist":"FALCO","rs_track":"Jeanny","rs_youtube_id":"Urw-iutHw5E","time":"05:47","rs_id":"20529705","f_time":"2024.10.23. 05:47","itunes_pic":"Music124\/v4\/f8\/72\/2b\/f8722b02-3ade-5f3b-112e-a85a4ec7330c\/mzi.yxwhhgww.jpg"},{"rs_artist":"JOE COCKER","rs_track":"You Can Leave Your Hat On","rs_youtube_id":"hfgwrdYUQ2A","time":"05:43","rs_id":"20529562","f_time":"2024.10.23. 05:43","itunes_pic":"Music41\/v4\/62\/8d\/14\/628d144b-4fc7-ff24-fec2-9c6b2b5ae911\/077778124351.jpg"},{"rs_artist":"ELTON JOHN & KIKI DEE","rs_track":"Don't Go Breaking My Heart","rs_youtube_id":"z0qW9P-uYfM","time":"05:38","rs_id":"20529395","f_time":"2024.10.23. 05:38","itunes_pic":"Music112\/v4\/f1\/2a\/0a\/f12a0a94-5c3f-82d7-4faf-38873cbf77fe\/06UMGIM01420.rgb.jpg"},{"rs_artist":"DON HENLEY","rs_track":"The Boys Of Summer","rs_youtube_id":"6RUIeX6UCT8","time":"05:34","rs_id":"20529244","f_time":"2024.10.23. 05:34","itunes_pic":"Music124\/v4\/97\/e2\/ea\/97e2ea42-0f53-7a97-dc37-6bc20c5abe01\/00602547138309.rgb.jpg"},{"rs_artist":"WET WET WET","rs_track":"Love Is All Around","rs_youtube_id":"h3gEkwhdXUE","time":"05:30","rs_id":"20529117","f_time":"2024.10.23. 05:30","itunes_pic":"Music4\/v4\/42\/38\/2d\/42382ddf-9f26-1c3d-08f9-4f0e57991ec7\/dj.pztkntum.jpg"},{"rs_artist":"HUEY LEWIS AND THE NEWS","rs_track":"The Power Of Love","rs_youtube_id":"wBl2QGAIx1s","time":"05:27","rs_id":"20528997","f_time":"2024.10.23. 05:27","itunes_pic":"Music\/y2005\/m05\/d04\/h02\/s06.aldmvbqs.jpg"},{"rs_artist":"DIRE STRAITS","rs_track":"Sultans Of Swing","rs_youtube_id":"h0ffIJ7ZO4U","time":"05:22","rs_id":"20528844","f_time":"2024.10.23. 05:22","itunes_pic":"Music\/47\/c3\/21\/mzi.ciyzkqao.jpg"},{"rs_artist":"ILSE DELANGE","rs_track":"I'm Not So Tough","rs_youtube_id":"paa2NRBA7eU","time":"05:19","rs_id":"20528710","f_time":"2024.10.23. 05:19","itunes_pic":"Music\/v4\/9b\/be\/cf\/9bbecf61-cff9-d962-9ee4-f32b7f8e5e1d\/887396551800.jpg"},{"rs_artist":"JOHN FARNHAM","rs_track":"You're The Voice","rs_youtube_id":"tbkOZTSvrHs","time":"05:15","rs_id":"20528589","f_time":"2024.10.23. 05:15","itunes_pic":"Music\/3e\/22\/87\/mzi.zsmadqqb.jpg"},{"rs_artist":"MADONNA","rs_track":"Papa Don't Preach","rs_youtube_id":"yzLT6_TQmq8","time":"05:11","rs_id":"20528442","f_time":"2024.10.23. 05:11","itunes_pic":"Music\/70\/eb\/ff\/mzi.wydfjkzd.jpg"},{"rs_artist":"QUEEN","rs_track":"The Show Must Go On","rs_youtube_id":"t99KH0TR-J4","time":"05:07","rs_id":"20528308","f_time":"2024.10.23. 05:07","itunes_pic":"Music115\/v4\/4d\/08\/2a\/4d082a9e-7898-1aa1-a02f-339810058d9e\/14DMGIM05632.rgb.jpg"},{"rs_artist":"SISTER SLEDGE","rs_track":"We Are Family","rs_youtube_id":"uyGY2NfYpeE","time":"05:04","rs_id":"20528189","f_time":"2024.10.23. 05:04","itunes_pic":"Music114\/v4\/e1\/c0\/b8\/e1c0b820-d12b-d595-a714-9b614c08645b\/mzi.uedebbso.jpg"},{"rs_artist":"FLEETWOOD MAC","rs_track":"Little Lies","rs_youtube_id":"uCGD9dT12C0","time":"05:01","rs_id":"20528062","f_time":"2024.10.23. 05:01","itunes_pic":"Music124\/v4\/7d\/5b\/04\/7d5b0401-b944-b628-8eb2-d0cb49fb6ca5\/603497925599.jpg"},{"rs_artist":"MC HAMMER","rs_track":"U Can't Touch This","rs_youtube_id":"otCpCn0l4Wo","time":"04:54","rs_id":"20527845","f_time":"2024.10.23. 04:54","itunes_pic":"Music122\/v4\/0c\/a5\/7c\/0ca57c94-601d-f973-eb79-3941573aac7c\/13UABIM74018.rgb.jpg"},{"rs_artist":"TOTO","rs_track":"I'll Be Over You","rs_youtube_id":"r7XhWUDj-Ts","time":"04:50","rs_id":"20527708","f_time":"2024.10.23. 04:50","itunes_pic":"Music114\/v4\/7e\/80\/d4\/7e80d4f5-4784-a9b7-c1fa-2f92890a5e15\/886444641500.jpg"},{"rs_artist":"EARTH WIND & FIRE","rs_track":"September","rs_youtube_id":"Gs069dndIYk","time":"04:47","rs_id":"20527570","f_time":"2024.10.23. 04:47","itunes_pic":"Music115\/v4\/e3\/43\/90\/e34390e9-6063-acf9-2f07-7bbeefaef9f2\/886444485722.jpg"},{"rs_artist":"KATE BUSH","rs_track":"Running Up That Hill","rs_youtube_id":"wp43OdtAAkM","time":"04:42","rs_id":"20527401","f_time":"2024.10.23. 04:42","itunes_pic":"Music126\/v4\/2c\/3e\/c9\/2c3ec991-0f6e-bec3-7eff-750f50c5b3a6\/cover.jpg"},{"rs_artist":"BL\u00d8F","rs_track":"Aan De Kust (Live)","rs_youtube_id":"nI8t-UDWdqQ","time":"04:38","rs_id":"20527271","f_time":"2024.10.23. 04:38","itunes_pic":"Music7\/v4\/00\/21\/9a\/00219a40-0bfd-2658-0d71-2b5c31fbbd6c\/00724383609857.jpg"},{"rs_artist":"ROBIN BECK","rs_track":"First Time","rs_youtube_id":"oXk-PPmH5ak","time":"04:35","rs_id":"20527142","f_time":"2024.10.23. 04:35","itunes_pic":"Music\/5e\/2a\/3c\/mzi.ltcgzotl.jpg"},{"rs_artist":"SURVIVOR","rs_track":"Eye Of The Tiger","rs_youtube_id":"btPJPFnesV4","time":"04:31","rs_id":"20527021","f_time":"2024.10.23. 04:31","itunes_pic":"Music125\/v4\/43\/ac\/a6\/43aca6ee-f013-4d96-bd57-8b6ba474ce04\/198000322663.jpg"},{"rs_artist":"BACKSTREET BOYS","rs_track":"As Long As You Love Me","rs_youtube_id":"0Gl2QnHNpkA","time":"04:28","rs_id":"20526887","f_time":"2024.10.23. 04:28","itunes_pic":"Music114\/v4\/59\/00\/53\/59005338-772d-2dd7-e2ff-674484629337\/012414158925.jpg"},{"rs_artist":"SUPERTRAMP","rs_track":"The Logical Song","rs_youtube_id":"pP8iUyb9Gn8","time":"04:24","rs_id":"20526755","f_time":"2024.10.23. 04:24","itunes_pic":"Music125\/v4\/09\/95\/b3\/0995b3e6-1dfd-7eed-e4fc-3ec7594c8fde\/06UMGIM10542.rgb.jpg"},{"rs_artist":"BELINDA CARLISLE","rs_track":"Heaven Is A Place On Earth","rs_youtube_id":"j2F4INQFjEI","time":"04:20","rs_id":"20526614","f_time":"2024.10.23. 04:20","itunes_pic":"Music115\/v4\/48\/88\/82\/48888281-17b1-4fd5-9573-95eb2acb0b9d\/06UMGIM07185.rgb.jpg"},{"rs_artist":"LIONEL RICHIE","rs_track":"All Night Long","rs_youtube_id":"nqAvFx3NxUM","time":"04:16","rs_id":"20526476","f_time":"2024.10.23. 04:16","itunes_pic":"Music125\/v4\/0d\/c0\/a3\/0dc0a301-d9e5-2980-5141-d8ddb1571398\/00602498607497.rgb.jpg"},{"rs_artist":"RED HOT CHILI PEPPERS","rs_track":"Under The Bridge","rs_youtube_id":"GLvohMXgcBo","time":"04:11","rs_id":"20526298","f_time":"2024.10.23. 04:11","itunes_pic":"Music115\/v4\/a0\/fe\/3f\/a0fe3ff1-d068-b00e-6265-0b53dd144dcf\/093624931997.jpg"},{"rs_artist":"CRUSADERS & RANDY CRAWFORD","rs_track":"Street Life","rs_youtube_id":"-iVR7WLsvAg","time":"04:08","rs_id":"20526170","f_time":"2024.10.23. 04:08","itunes_pic":"Music124\/v4\/c2\/ae\/b2\/c2aeb2ce-c9dd-91a4-41a2-08e23a7d1584\/00602517184053.rgb.jpg"},{"rs_artist":"U2","rs_track":"I Still Haven't Found What I'm Looking For","rs_youtube_id":"e3-5YC_oHjE","time":"04:04","rs_id":"20526025","f_time":"2024.10.23. 04:04","itunes_pic":"Music115\/v4\/8f\/e2\/c3\/8fe2c384-f6cb-9af7-371d-2b6a9b204e59\/17UMGIM79292.rgb.jpg"},{"rs_artist":"DAVID BOWIE","rs_track":"China Girl","rs_youtube_id":"_YC3sTbAPcU","time":"03:57","rs_id":"20525813","f_time":"2024.10.23. 03:57","itunes_pic":"Features115\/v4\/fc\/65\/98\/fc6598f9-706b-48a2-dc37-9854f703b21e\/dj.xnockfyi.jpg"},{"rs_artist":"BANGLES","rs_track":"Eternal Flame","rs_youtube_id":"PSoOFn3wQV4","time":"03:54","rs_id":"20525688","f_time":"2024.10.23. 03:54","itunes_pic":"Music124\/v4\/b2\/2a\/57\/b22a5707-86ae-2719-e661-b7c4a91773c5\/mzi.gizvcfrx.jpg"},{"rs_artist":"BOSTON","rs_track":"More Than A Feeling","rs_youtube_id":"t4QK8RxCAwo","time":"03:49","rs_id":"20525517","f_time":"2024.10.23. 03:49","itunes_pic":"Music126\/v4\/e3\/08\/9a\/e3089ac9-a820-5ee9-64be-39500ad8a5e2\/886444824972.jpg"},{"rs_artist":"LUTRICIA MCNEAL","rs_track":"Ain't That Just The Way","rs_youtube_id":"XNSAdIURFwk","time":"03:46","rs_id":"20525401","f_time":"2024.10.23. 03:46","itunes_pic":"Music211\/v4\/df\/96\/f2\/df96f225-017f-42e6-d46e-21df46f01d85\/3617054956305_cover.jpg"},{"rs_artist":"BEACH BOYS","rs_track":"Kokomo","rs_youtube_id":"fJWmbLS2_ec","time":"03:42","rs_id":"20525268","f_time":"2024.10.23. 03:42","itunes_pic":"Music122\/v4\/e7\/23\/02\/e7230264-d5a9-a3b0-9eee-c6af522781fb\/13UABIM59247.rgb.jpg"},{"rs_artist":"BRUCE SPRINGSTEEN","rs_track":"I'm On Fire","rs_youtube_id":"lrpXArn3hII","time":"03:40","rs_id":"20525179","f_time":"2024.10.23. 03:40","itunes_pic":"Music115\/v4\/32\/72\/68\/327268ba-b9dd-b322-2a16-bdd0212df48c\/074643865326.jpg"},{"rs_artist":"BILLY OCEAN","rs_track":"Love Really Hurts Without You","rs_youtube_id":"q5uMOOQ6MV0","time":"03:37","rs_id":"20525070","f_time":"2024.10.23. 03:37","itunes_pic":"Music115\/v4\/a9\/ee\/fd\/a9eefd6d-667d-0d6d-87ff-3da7a5d8361f\/mzi.abkecwqm.jpg"},{"rs_artist":"JOAN OSBORNE","rs_track":"One Of Us","rs_youtube_id":"aDdOnl0bHO4","time":"03:32","rs_id":"20524900","f_time":"2024.10.23. 03:32","itunes_pic":"Music125\/v4\/73\/7b\/e8\/737be8fa-811b-a143-992a-948ba265f0a0\/00731452669926.rgb.jpg"},{"rs_artist":"RYAN PARIS","rs_track":"Dolce Vita","rs_youtube_id":"EXmABxvHTG4","time":"03:29","rs_id":"20524767","f_time":"2024.10.23. 03:29","itunes_pic":"Music\/ac\/44\/03\/mzi.izvymzyy.jpg"},{"rs_artist":"ERIC CLAPTON","rs_track":"Wonderful Tonight","rs_youtube_id":"UprwkbzUX6g","time":"03:25","rs_id":"20524653","f_time":"2024.10.23. 03:25","itunes_pic":"Music115\/v4\/2b\/55\/08\/2b550878-8bad-b40f-9a58-d63aca53c824\/00602498206034.rgb.jpg"},{"rs_artist":"MICHAEL JACKSON","rs_track":"Don't Stop 'Til You Get Enough","rs_youtube_id":"yURRmWtbTbo","time":"03:21","rs_id":"20524499","f_time":"2024.10.23. 03:21","itunes_pic":"Music125\/v4\/3d\/9d\/38\/3d9d3811-71f0-3a0e-1ada-3004e56ff852\/827969428726.jpg"},{"rs_artist":"JOHN PARR","rs_track":"St Elmo's Fire (Man In Motion)","rs_youtube_id":"dx7vNdAb5e4","time":"03:17","rs_id":"20524351","f_time":"2024.10.23. 03:17","itunes_pic":"Music114\/v4\/fa\/27\/fc\/fa27fc18-eedb-97ab-218f-556bf962fd08\/680569833938_cover.tif"},{"rs_artist":"IRENE CARA","rs_track":"Flashdance (What A Feeling)","rs_youtube_id":"miax0Jpe5mA","time":"03:13","rs_id":"20524202","f_time":"2024.10.23. 03:13","itunes_pic":"Music122\/v4\/a6\/89\/fb\/a689fb59-04a8-dd18-d4d4-94c0918f1463\/3256.jpg"},{"rs_artist":"ALANIS MORISSETTE","rs_track":"Ironic","rs_youtube_id":"Jne9t8sHpUc","time":"03:09","rs_id":"20524065","f_time":"2024.10.23. 03:09","itunes_pic":"Features124\/v4\/5f\/3b\/ca\/5f3bca60-024c-d4aa-d638-6d58e7e81461\/mza_1406686761081396977.jpg"},{"rs_artist":"BONEY M","rs_track":"Sunny","rs_youtube_id":"hutlaauYa2c","time":"03:06","rs_id":"20523950","f_time":"2024.10.23. 03:06","itunes_pic":"Music115\/v4\/b7\/86\/45\/b786452a-a723-eaed-8170-cdc261367eb7\/886443575578.jpg"},{"rs_artist":"BRYAN ADAMS","rs_track":"Heaven","rs_youtube_id":"s6TtwR2Dbjg","time":"03:02","rs_id":"20523824","f_time":"2024.10.23. 03:02","itunes_pic":"Music125\/v4\/fc\/d8\/61\/fcd86101-ffbb-9a17-ca3d-2c1aa696481c\/00731454083126.rgb.jpg"},{"rs_artist":"BILLY JOEL","rs_track":"My Life","rs_youtube_id":"h3JFEfdK_Ls","time":"02:56","rs_id":"20523642","f_time":"2024.10.23. 02:56","itunes_pic":"Music125\/v4\/f0\/7a\/54\/f07a54ab-3ebc-6813-e515-86200b8138fc\/dj.uthntyfe.jpg"},{"rs_artist":"MURRAY HEAD","rs_track":"One Night In Bangkok","rs_youtube_id":"rgc_LRjlbTU","time":"02:53","rs_id":"20523508","f_time":"2024.10.23. 02:53","itunes_pic":"Music60\/v4\/23\/6f\/58\/236f5802-7792-58cf-0ca6-a4764ba813c4\/cover.jpg"},{"rs_artist":"ACE OF BASE","rs_track":"All That She Wants","rs_youtube_id":"d73tiBBzvFM","time":"02:49","rs_id":"20523389","f_time":"2024.10.23. 02:49","itunes_pic":"Music126\/v4\/ca\/57\/8e\/ca578e1c-9874-6201-8207-7a7be36cf798\/cover.jpg"},{"rs_artist":"COMMODORES","rs_track":"Nightshift","rs_youtube_id":"FrkEDe6Ljqs","time":"02:45","rs_id":"20523227","f_time":"2024.10.23. 02:45","itunes_pic":"Music124\/v4\/b5\/22\/ce\/b522ce38-62d1-d637-1ba9-430b194dbaf4\/00602547316738.rgb.jpg"},{"rs_artist":"KOOL & THE GANG","rs_track":"Celebration","rs_youtube_id":"3GwjfUFyY6M","time":"02:42","rs_id":"20523115","f_time":"2024.10.23. 02:42","itunes_pic":"Music124\/v4\/48\/c9\/c3\/48c9c3a6-35e7-fd96-f3c8-80956c70e6ca\/00602567825494.rgb.jpg"},{"rs_artist":"QUEEN","rs_track":"Radio Ga Ga","rs_youtube_id":"azdwsXLmrHE","time":"02:38","rs_id":"20522985","f_time":"2024.10.23. 02:38","itunes_pic":"Music115\/v4\/4d\/08\/2a\/4d082a9e-7898-1aa1-a02f-339810058d9e\/14DMGIM05632.rgb.jpg"},{"rs_artist":"ENRIQUE IGLESIAS","rs_track":"Rhythm Divine","rs_youtube_id":"UZrzOZaI7UE","time":"02:34","rs_id":"20522848","f_time":"2024.10.23. 02:34","itunes_pic":"Music124\/v4\/4b\/ee\/6d\/4bee6de5-f0c2-de3b-a6cd-7d5060b3bd14\/00606949054021.rgb.jpg"},{"rs_artist":"FRANK BOEIJEN GROEP","rs_track":"Kronenburg Park","rs_youtube_id":"pgmv1mnaRaA","time":"02:30","rs_id":"20522702","f_time":"2024.10.23. 02:30","itunes_pic":"Music116\/v4\/10\/e7\/c4\/10e7c4e0-c605-96dc-1b35-050ed85798f6\/886446372396.jpg"},{"rs_artist":"SIMPLE MINDS","rs_track":"Don't You (Forget About Me)","rs_youtube_id":"CdqoNKCCt7A","time":"02:26","rs_id":"20522551","f_time":"2024.10.23. 02:26","itunes_pic":"Music49\/v4\/cf\/7c\/6f\/cf7c6f12-5f35-797f-8563-810456ce0717\/dj.tgjrbpvo.jpg"},{"rs_artist":"HANSON","rs_track":"Mmmbop","rs_youtube_id":"NHozn0YXAeE","time":"02:22","rs_id":"20522397","f_time":"2024.10.23. 02:22","itunes_pic":"Music116\/v4\/8c\/a2\/3f\/8ca23fab-6c25-3d22-0b53-fe649c0f05e2\/06UMGIM19285.rgb.jpg"},{"rs_artist":"JOHN TRAVOLTA & OLIVIA NEWTON-JOHN","rs_track":"You're The One That I Want","rs_youtube_id":"itRFjzQICJU","time":"02:19","rs_id":"20522314","f_time":"2024.10.23. 02:19","itunes_pic":"Music125\/v4\/25\/d5\/dc\/25d5dc67-bf45-6e42-510e-bcf6bcee1cda\/00602547377951.rgb.jpg"},{"rs_artist":"STEVIE WONDER","rs_track":"I Just Called To Say I Love You","rs_youtube_id":"1bGOgY1CmiU","time":"02:15","rs_id":"20522143","f_time":"2024.10.23. 02:15","itunes_pic":"Music128\/v4\/0a\/c6\/b4\/0ac6b4f3-a86f-ba5e-bbfd-61c61f6a33b0\/00602577177392.rgb.jpg"},{"rs_artist":"WHAM!","rs_track":"The Edge Of Heaven","rs_youtube_id":"cCqEyJc-wdk","time":"02:12","rs_id":"20522026","f_time":"2024.10.23. 02:12","itunes_pic":"Music125\/v4\/6e\/c3\/66\/6ec3666f-7b4d-49b8-808f-9e40774443e3\/mzi.ynkcpjdq.jpg"},{"rs_artist":"REMBRANDTS","rs_track":"I'll Be There For You","rs_youtube_id":"q-9kPks0IfE","time":"02:09","rs_id":"20521926","f_time":"2024.10.23. 02:09","itunes_pic":"Music62\/v4\/96\/52\/a7\/9652a72e-51dc-517b-343a-e7474af37084\/dj.yzmsvlvd.jpg"},{"rs_artist":"HOT CHOCOLATE","rs_track":"You Sexy Thing","rs_youtube_id":"4DwEni2N_-A","time":"02:05","rs_id":"20521791","f_time":"2024.10.23. 02:05","itunes_pic":"Music115\/v4\/9d\/26\/11\/9d2611a1-cbfd-fcaf-1c80-0d6df913a43c\/mzm.jtydtbxn.jpg"},{"rs_artist":"UB40 & CHRISSIE HYNDE","rs_track":"I Got You Babe","rs_youtube_id":"2aP4GaAruws","time":"02:02","rs_id":"20521680","f_time":"2024.10.23. 02:02","itunes_pic":"Music114\/v4\/8e\/fc\/d7\/8efcd7fa-9922-ecbe-7024-d777d9b154d6\/13UABIM50818.rgb.jpg"},{"rs_artist":"LEVEL 42","rs_track":"Running In The Family","rs_youtube_id":"x4m41bBPJvA","time":"01:56","rs_id":"20521466","f_time":"2024.10.23. 01:56","itunes_pic":"Music115\/v4\/6e\/81\/bc\/6e81bc85-010a-d657-f8f6-c6edfc6a1664\/00042284139922.rgb.jpg"},{"rs_artist":"MIDNIGHT OIL","rs_track":"Beds Are Burning","rs_youtube_id":"ejorQVy3m8E","time":"01:52","rs_id":"20521316","f_time":"2024.10.23. 01:52","itunes_pic":"Music221\/v4\/d7\/6d\/0c\/d76d0c5f-de29-8149-d79a-923e5b5cea45\/4099496662003.jpg"},{"rs_artist":"ABBA","rs_track":"Mamma Mia","rs_youtube_id":"J91ti_MpdHA","time":"01:48","rs_id":"20521192","f_time":"2024.10.23. 01:48","itunes_pic":"Music125\/v4\/3e\/be\/e2\/3ebee2d8-56a0-98b2-2427-b384ea708725\/00602567666585.rgb.jpg"},{"rs_artist":"BOYZ II MEN","rs_track":"End Of The Road","rs_youtube_id":"zDKO6XYXioc","time":"01:45","rs_id":"20521064","f_time":"2024.10.23. 01:45","itunes_pic":"Music114\/v4\/53\/fe\/26\/53fe267e-6f41-87fa-3f46-c183f9de0cd0\/8718522038266.jpg"},{"rs_artist":"DENIECE WILLIAMS","rs_track":"Let's Hear It For The Boy","rs_youtube_id":"gI7YHZVc7mM","time":"01:40","rs_id":"20520905","f_time":"2024.10.23. 01:40","itunes_pic":"Music124\/v4\/8c\/52\/92\/8c5292a8-8a85-69e3-b618-7eab1f959f24\/mzi.wqmsznel.jpg"},{"rs_artist":"HEART","rs_track":"Alone","rs_youtube_id":"1Cw1ng75KP0","time":"01:37","rs_id":"20520775","f_time":"2024.10.23. 01:37","itunes_pic":"Music125\/v4\/2b\/d4\/d5\/2bd4d595-6839-5d35-a601-a74045f1f7b1\/00724352680351.rgb.jpg"},{"rs_artist":"BARRY WHITE","rs_track":"Can't Get Enough Of Your Love","rs_youtube_id":"x0I6mhZ5wMw","time":"01:32","rs_id":"20520624","f_time":"2024.10.23. 01:32","itunes_pic":"Music115\/v4\/89\/3f\/cf\/893fcf8b-b0d0-d91e-2f3f-eea43a9d7d41\/00602567825562.rgb.jpg"},{"rs_artist":"DEPECHE MODE","rs_track":"Enjoy The Silence","rs_youtube_id":"aGSKrC7dGcY","time":"01:28","rs_id":"20520490","f_time":"2024.10.23. 01:28","itunes_pic":"Music126\/v4\/43\/61\/fc\/4361fcb8-024d-fdc7-56bd-ca0d1a1733d1\/0.jpg"},{"rs_artist":"EROS RAMAZZOTTI","rs_track":"Ma Che Bello Questo Amore","rs_youtube_id":"BhmloO5m158","time":"01:24","rs_id":"20520344","f_time":"2024.10.23. 01:24","itunes_pic":"Features\/7e\/3a\/de\/dj.baesfcdo.jpg"},{"rs_artist":"MADONNA","rs_track":"Like A Prayer","rs_youtube_id":"79fzeNUqQbQ","time":"01:21","rs_id":"20520207","f_time":"2024.10.23. 01:21","itunes_pic":"Music114\/v4\/20\/3c\/f5\/203cf53d-689e-528f-29d7-ba33758254aa\/mzi.rotbotfl.jpg"},{"rs_artist":"PATRICK HERNANDEZ","rs_track":"Born To Be Alive","rs_youtube_id":"9UaJAnnipkY","time":"01:18","rs_id":"20520097","f_time":"2024.10.23. 01:18","itunes_pic":"Music116\/v4\/65\/1e\/f5\/651ef54a-e88b-5043-c9a2-af7c662aa382\/cover.jpg"},{"rs_artist":"KATRINA & THE WAVES","rs_track":"Walking On Sunshine","rs_youtube_id":"iPUmE-tne5U","time":"01:14","rs_id":"20519971","f_time":"2024.10.23. 01:14","itunes_pic":"Music124\/v4\/f6\/b6\/37\/f6b6378c-9b34-72fb-9abe-4a6d6042ad53\/13ULAIM49571.rgb.jpg"},{"rs_artist":"CROWDED HOUSE","rs_track":"Don't Dream It's Over","rs_youtube_id":"J9gKyRmic20","time":"01:10","rs_id":"20519833","f_time":"2024.10.23. 01:10","itunes_pic":"Music124\/v4\/91\/42\/09\/91420918-380f-c05a-3225-78b27c792774\/13UAEIM58114.rgb.jpg"},{"rs_artist":"R.E.M.","rs_track":"Losing My Religion","rs_youtube_id":"xwtdhWltSIg","time":"01:07","rs_id":"20519705","f_time":"2024.10.23. 01:07","itunes_pic":"Music115\/v4\/d4\/9c\/f6\/d49cf63f-a412-5737-9392-1576c297b475\/00888072396272.rgb.jpg"},{"rs_artist":"ROGER GLOVER","rs_track":"Love Is All","rs_youtube_id":"RW9OYsMn4ds","time":"01:04","rs_id":"20519604","f_time":"2024.10.23. 01:04","itunes_pic":"Music124\/v4\/ed\/8f\/e7\/ed8fe766-a5aa-aecb-c1cb-ddb4be741606\/WITW.jpg"},{"rs_artist":"BRUCE SPRINGSTEEN","rs_track":"Born In The U.S.A.","rs_youtube_id":"xn0UpiBtiA4","time":"01:00","rs_id":"20519469","f_time":"2024.10.23. 01:00","itunes_pic":"Music124\/v4\/41\/cf\/0e\/41cf0e68-b332-9777-44b3-01c8936d626c\/09UMGIM27654.rgb.jpg"},{"rs_artist":"GEORGE BAKER SELECTION","rs_track":"Little Green Bag","rs_youtube_id":"kipjrg5O0A4","time":"00:54","rs_id":"20519270","f_time":"2024.10.23. 00:54","itunes_pic":"Music\/b8\/3d\/9b\/mzi.abwtnwtk.jpg"},{"rs_artist":"YAZOO","rs_track":"Don't Go","rs_youtube_id":"_sQGwDeambg","time":"00:52","rs_id":"20519182","f_time":"2024.10.23. 00:52","itunes_pic":""},{"rs_artist":"JANET JACKSON","rs_track":"Together Again","rs_youtube_id":"7SXKHiPQPhk","time":"00:48","rs_id":"20519031","f_time":"2024.10.23. 00:48","itunes_pic":"Music122\/v4\/21\/ba\/cf\/21bacf43-5878-e76b-e018-ca936a8243a7\/22UMGIM92303.rgb.jpg"},{"rs_artist":"PRINCE","rs_track":"Raspberry Beret","rs_youtube_id":"l7vRSu_wsNc","time":"00:44","rs_id":"20518919","f_time":"2024.10.23. 00:44","itunes_pic":"Music124\/v4\/de\/3c\/76\/de3c7606-c57a-09d1-0ca0-32e020fc7660\/886448892939.jpg"},{"rs_artist":"10CC","rs_track":"Dreadlock Holiday","rs_youtube_id":"fUNTk5xsxk4","time":"00:40","rs_id":"20518763","f_time":"2024.10.23. 00:40","itunes_pic":"Music114\/v4\/e9\/44\/2c\/e9442c9d-426e-e830-fcbc-d5d7ae6d2eac\/06UMGIM09374.rgb.jpg"},{"rs_artist":"CULTURE CLUB","rs_track":"Karma Chameleon","rs_youtube_id":"JmcA9LIIXWw","time":"00:37","rs_id":"20518633","f_time":"2024.10.23. 00:37","itunes_pic":"Music125\/v4\/f2\/22\/23\/f222233c-ba5a-55bb-2410-f176c02e90c4\/13UADIM60816.rgb.jpg"},{"rs_artist":"CRANBERRIES","rs_track":"Ode To My Family","rs_youtube_id":"Zz-DJr1Qs54","time":"00:32","rs_id":"20518460","f_time":"2024.10.23. 00:32","itunes_pic":"Music115\/v4\/10\/ca\/47\/10ca4719-e70e-6806-5c52-308806cccd3c\/06UMGIM09433.rgb.jpg"},{"rs_artist":"NIK KERSHAW","rs_track":"The Riddle","rs_youtube_id":"bDygS0a6Tgo","time":"00:28","rs_id":"20518334","f_time":"2024.10.23. 00:28","itunes_pic":"Music128\/v4\/cb\/fd\/59\/cbfd5904-4b62-e329-098d-2359b36bde1e\/00008811045227.rgb.jpg"},{"rs_artist":"U2","rs_track":"With Or Without You","rs_youtube_id":"ujNeHIo7oTE","time":"00:24","rs_id":"20518172","f_time":"2024.10.23. 00:24","itunes_pic":"Music118\/v4\/e5\/da\/2e\/e5da2ed5-eaeb-31fb-4784-2742cb79ca3b\/dj.jhjeahph.jpg"},{"rs_artist":"SIXPENCE NONE THE RICHER","rs_track":"Kiss Me","rs_youtube_id":"Jnq9wPDoDKg","time":"00:20","rs_id":"20518048","f_time":"2024.10.23. 00:20","itunes_pic":"Music125\/v4\/3e\/90\/d9\/3e90d92a-69f8-75e8-f681-b773e05c50c7\/080688551261.png"},{"rs_artist":"GLORIA GAYNOR","rs_track":"I Will Survive","rs_youtube_id":"6dYWe1c3OyU","time":"00:17","rs_id":"20517943","f_time":"2024.10.23. 00:17","itunes_pic":"Music128\/v4\/33\/12\/df\/3312dfbf-2cd2-e149-1ccb-9688e2a60980\/00731454913720.rgb.jpg"},{"rs_artist":"FICTION FACTORY","rs_track":"(Feels Like) Heaven","rs_youtube_id":"KQBoeBgb0uk","time":"00:14","rs_id":"20517801","f_time":"2024.10.23. 00:14","itunes_pic":"Music124\/v4\/b0\/b3\/3e\/b0b33e24-d435-ffd8-0910-24371fcb8308\/mzi.zfnsgvjb.jpg"},{"rs_artist":"IRENE CARA","rs_track":"Fame","rs_youtube_id":"ChhCpSVrjvU","time":"00:10","rs_id":"20517668","f_time":"2024.10.23. 00:10","itunes_pic":"Video\/f0\/1c\/02\/mzi.jnixjkkt.jpg"},{"rs_artist":"NATALIE IMBRUGLIA","rs_track":"Torn","rs_youtube_id":"VV1XWJN3nJo","time":"00:06","rs_id":"20517534","f_time":"2024.10.23. 00:06","itunes_pic":"Music125\/v4\/11\/5d\/f1\/115df15e-e05f-b0f1-ae66-3ad2c5e969b4\/mzi.ihaejhxb.jpg"},{"rs_artist":"JIMMY BO HORNE","rs_track":"Dance Across The Floor","rs_youtube_id":"ykmszqag1BU","time":"00:04","rs_id":"20517431","f_time":"2024.10.23. 00:04","itunes_pic":"Music\/v4\/d4\/35\/51\/d4355113-34f7-3e29-d083-04b6f9afd318\/894231749926.jpg"},{"rs_artist":"BON JOVI","rs_track":"Livin' On A Prayer","rs_youtube_id":"lDK9QqIzhwk","time":"00:00","rs_id":"20517302","f_time":"2024.10.23. 00:00","itunes_pic":"Music112\/v4\/40\/16\/3e\/40163e24-6985-b785-d4ea-cbae07d74812\/06UMGIM05422.rgb.jpg"}]